{"title":"Idioms","url":"http://www.ang.pl/slownictwo/idiomy","content":[{"a1":"keep sth under one\u0027s hat","a2":"trzymać coś w tajemnicy","a3":"They tried to keep it under their hat but it soon became obvious that she is pregnant.","id":"14a5ea89","ref":"767c2d5b"},{"a1":"the other side of the coin","a2":"druga strona medalu","a3":"Fame has the other side of the coin as well.","id":"a66ebba0","ref":"767c2d5b"},{"a1":"make up one\u0027s mind","a2":"postanowić, zdecydować się","a3":"He finally made up his mind!","id":"cf099852","ref":"767c2d5b"},{"a1":"change a fly into an elephant","a2":"robić z igły widły","a3":"Gee! She doesn\u0027t have an evening dress?! It\u0027s just friends\u0027 party - why does she have to change a fly into an elephant!","id":"e54c0819","ref":"767c2d5b"},{"a1":"easier said than done","a2":"łatwiej powiedzieć, niż zrobić","a3":"I know it\u0027s easier said than done but in my opinion you should challenge it.","id":"73d517fd","ref":"767c2d5b"},{"a1":"on thin ice","a2":"na niepewnym gruncie","a3":"His rude answer put him on thin ice in the company.","id":"1df5d153","ref":"767c2d5b"},{"a1":"hit the nail on the head","a2":"trafić w sedno","a3":"Right! Nothing to add! You\u0027ve just hit the nail on the head!","id":"c11fe2c5","ref":"767c2d5b"},{"a1":"it goes without saying","a2":"to oczywiste, nie ma dwóch zdań","a3":"Oh, Amy you should marry him! It goes without saying.","id":"a982cda9","ref":"767c2d5b"},{"a1":"leave no stone unturned","a2":"poruszyć niebo i ziemię, zastosować wszystkie środki","a3":"I may need to leave no stone unturned but I will find this book!","id":"5cd28ce4","ref":"767c2d5b"},{"a1":"put in jeopardy","a2":"narazić na niebiezpieczeństwo","a3":"As the Ambassador didn\u0027t want to put the staff in jeopardy, they were all dismissed and sent home.","id":"d02d7bca","ref":"767c2d5b"},{"a1":"cry for the moon","a2":"chcieć gwiazdki z nieba","a3":"Oh, come on! Be realistic! It\u0027s like crying for the moon! We cannot afford it.","id":"496ef4d9","ref":"767c2d5b"},{"a1":"promise wonders","a2":"obiecywać złote góry","a3":"She was very disappointed with the job. They promised wonders when they hired her but nothing came true...","id":"e866cbf4","ref":"767c2d5b"},{"a1":"self-made man","a2":"człowiek, który sam się dorobił, zrobił karierę","a3":"The idea of self-made man is one of the most important concepts in America.","id":"8de2e3a4","ref":"767c2d5b"},{"a1":"read sb\u0027s hand","a2":"wróżyć z ręki","a3":"She wanted the Gypsy woman to read her hand and find out about her future.","id":"086b29a8","ref":"767c2d5b"},{"a1":"shed blood","a2":"przelewać krew","a3":"Much blood was shed during the war.","id":"7a58fbbb","ref":"767c2d5b"},{"a1":"ups and downs","a2":"radości i smutki, zmienne koleje losu","a3":"Their relationship was full of ups and downs.","id":"efd09996","ref":"767c2d5b"},{"a1":"take sth for granted","a2":"przyjmować coś za rzecz oczywistą, naturalną","a3":"Never take love for granted. It has to be cherished to last.","id":"ceb09c00","ref":"767c2d5b"},{"a1":"put sb/be at a disadvantage","a2":"stawiać kogoś/być w niekorzystnej sytuacji","a3":"The fact that the company\u0027s office was moved to the different part of the town has put me at a disadvantage. Now I have to commute almost one hour to get there.","id":"287f081d","ref":"767c2d5b"},{"a1":"on the market","a2":"w sprzedaży, na rynku","a3":"At the moment this is the best camera on the market.","id":"99d6982e","ref":"767c2d5b"},{"a1":"little by little","a2":"stopniowo","a3":"After the accident her strength returned little by little.","id":"f84055cc","ref":"767c2d5b"},{"a1":"at sb\u0027s expense","a2":"1. na czyjś rachunek; 2. czyimś kosztem","a3":"The trip is at company\u0027s expense. We are always making jokes at Mark\u0027s expense.","id":"8b967236","ref":"767c2d5b"},{"a1":"if you like","a2":"jeśli masz na to ochotę","a3":"- Shall we stop for a rest? - Yes, if you like.","id":"d4a31225","ref":"767c2d5b"},{"a1":"at all costs","a2":"za wszelką cenę","a3":"We must win at all costs.","id":"c9bde399","ref":"767c2d5b"},{"a1":"at the top of your voice","a2":"na całe gardło","a3":"They are always discussing things at the top of their voices. It\u0027s so annoying.","id":"0126ff56","ref":"767c2d5b"},{"a1":"burst out laughing","a2":"wybuchać śmiechem","a3":"The movie was so funny that finally even Susan burst out laughing.","id":"61559e24","ref":"767c2d5b"},{"a1":"catch sb red-handed","a2":"złapać kogoś na gorącym uczynku","a3":"The trial won\u0027t take long as the defendant was caught red-handed.","id":"e9bec5f5","ref":"767c2d5b"},{"a1":"high and low","a2":"wszędzie","a3":"We\u0027ve searched high and low for this book.","id":"486649b7","ref":"767c2d5b"},{"a1":"without fail","a2":"niezawodnie","a3":"The postman always comes at 10 o\u0027clock without fail.","id":"60e9ca43","ref":"767c2d5b"},{"a1":"the naked eye","a2":"gołym okiem","a3":"Bacteria are too small to be seen with the naked eye.","id":"6a95eae7","ref":"767c2d5b"},{"a1":"with a vengeance","a2":"z podwójną siłą","a3":"After a week of good weather winter has returned with a vengeance today.","id":"b67085ee","ref":"767c2d5b"},{"a1":"gnash your teeth","a2":"zgrzytać zębami","a3":"Hell is so terrible that those who go there will weep and gnash their teeth. Mary gnashes her teeth in frustration.","id":"6de8bc03","ref":"767c2d5b"},{"a1":"be in the red","a2":"mieć debet (w banku)","a3":"It has been announced that the company will still be in the red for the rest of this year.","id":"bf5d29a7","ref":"767c2d5b"},{"a1":"a bad patch","a2":"zła passa","a3":"Last season we hit a bad patch of form and suddenly we were out of the Champions League.","id":"12d65962","ref":"767c2d5b"},{"a1":"after your own heart","a2":"bratnia dusza","a3":"She loves books too - she\u0027s a woman after my own heart!","id":"8144d522","ref":"767c2d5b"},{"a1":"in haste","a2":"w pośpiechu","a3":"I\u0027m writing in haste to let you know that I won\u0027t come on Friday.","id":"2fa68fb6","ref":"767c2d5b"},{"a1":"inside out","a2":"1. na lewą stronę, 2. (znać) na wylot","a3":"He\u0027s a real computer freak - he knows them inside out.","id":"e976dcec","ref":"767c2d5b"},{"a1":"make amends","a2":"wynagradzać szkodę/szkody","a3":"He went to him and begged his forgiveness, saying he would do anything he could to make amends.","id":"51207d6c","ref":"767c2d5b"},{"a1":"ease sb\u0027s mind","a2":"uspokajać kogoś","a3":"The doctor tried to ease his mind about his daughter\u0027s illness.","id":"f418d52e","ref":"767c2d5b"},{"a1":"a ray of hope","a2":"promyk nadziei","a3":"There is a ray of hope for humanity after all. Thank you so much for the ray of hope that shines in your message.","id":"1abb181b","ref":"767c2d5b"},{"a1":"out of print","a2":"wyczerpany nakład książki","a3":"I\u0027m sorry but the book you\u0027ve ordered is out of print.","id":"12225b71","ref":"767c2d5b"},{"a1":"get on sb\u0027s nerves","a2":"działać (komuś) na nerwy","a3":"Turn that music down! It\u0027s getting on my nerves.","id":"7b451c79","ref":"767c2d5b"},{"a1":"have something on the brain","a2":"chodzić komuś po głowie","a3":"Do you know this song? I\u0027ve had it on my brain all day.","id":"2b688cb6","ref":"767c2d5b"},{"a1":"rat race","a2":"wyścig szczurów","a3":"After years in the rat race she\u0027s finally decided to quit and spend more time with her family.","id":"a46d6dd5","ref":"767c2d5b"},{"a1":"get the message","a2":"załapać, zrozumieć coś","a3":"He finally got the message and left Mary and John alone together.","id":"7e65474e","ref":"767c2d5b"},{"a1":"ask for trouble","a2":"prosić się o kłopoty","a3":"Not wearing a seat belt is just asking for trouble.","id":"e6331a82","ref":"767c2d5b"},{"a1":"pay tribute to sb/sth","a2":"wyrażać (komuś) swoje uznanie, oddawać hołd","a3":"In 1992, a concert was held at Wembley Stadium to pay tribute to Freddie Mercury from Queen.","id":"44e04150","ref":"767c2d5b"},{"a1":"in bulk","a2":"hurtowo","a3":"If you buy in bulk, it\u0027s 20% cheaper.","id":"d27b4109","ref":"767c2d5b"},{"a1":"give somebody a ring","a2":"zadzwonić do kogoś","a3":"I\u0027ll give you a ring in the evening.","id":"9508498b","ref":"767c2d5b"},{"a1":"all year round","a2":"przez cały rok","a3":"Most of the hotels are open all year round.","id":"1cfe07d3","ref":"767c2d5b"},{"a1":"all of a sudden","a2":"nagle","a3":"All of a sudden the lights went out.","id":"5a7a31f6","ref":"767c2d5b"},{"a1":"as a matter of fact","a2":"prawdę mówiąc, w rzeczywistości","a3":"As a matter of fact, I love him very much.","id":"e629538d","ref":"767c2d5b"},{"a1":"be quits (with somebody)","a2":"być kwita","a3":"You give me 10 zloty and we\u0027re quits.","id":"436bb4a1","ref":"767c2d5b"},{"a1":"by courtesy of","a2":"dzięki uprzejmości, za zgodą","a3":"These pictures are being shown by courtesy of CNN.","id":"6ff08367","ref":"767c2d5b"},{"a1":"on location","a2":"(o programie, filmie) w plenerze","a3":"The series was filmed on location in Sweden.","id":"172e9a9e","ref":"767c2d5b"},{"a1":"go to waste","a2":"marnować się","a3":"I can\u0027t bear to see good food going to waste!","id":"082a45c2","ref":"767c2d5b"},{"a1":"on impulse","a2":"spontanicznie","a3":"When the weather is nice it\u0027s fun to go away on impulse.","id":"4d1760e7","ref":"767c2d5b"},{"a1":"trial and error","a2":"metoda prób i błędów","a3":"I found the answer by trial and error, which obviously took little more time.","id":"e63c8bef","ref":"767c2d5b"},{"a1":"snap one\u0027s fingers","a2":"pstrykać palcami","a3":"Music often inspires people to clap or snap their fingers.","id":"5b09840c","ref":"767c2d5b"},{"a1":"let something slip","a2":"wygadać się","a3":"He let slip that he had been in prison.","id":"ecc9e8d2","ref":"767c2d5b"},{"a1":"heave a sigh","a2":"wzdychać (głęboko)","a3":"She heaved a sigh of relief when she heard the good news.","id":"122ba5eb","ref":"767c2d5b"},{"a1":"be under the illusion","a2":"łudzić się","a3":"I think Mark\u0027s under the illusion that he will be the new director.","id":"d1faa4c6","ref":"767c2d5b"},{"a1":"not be sb\u0027s cup of tea","a2":"nie być w czyimś guście","a3":"In fact, horror films aren\u0027t my cup of tea.","id":"132f7179","ref":"767c2d5b"},{"a1":"make a fool of somebody/yourself","a2":"robić z kogoś/siebie głupka","a3":"Stop that before you make a fool of yourself!","id":"542cec6e","ref":"767c2d5b"},{"a1":"a walk of life","a2":"sfera społeczna","a3":"He has friends from many different walks of life.","id":"97c7d1c5","ref":"767c2d5b"},{"a1":"on your own initiative","a2":"z własnej inicjatywy","a3":"She realized that she had never done anything on her own initiative without the motivation of someone else.","id":"9412a62f","ref":"767c2d5b"},{"a1":"in vain","a2":"na próżno","a3":"The doctors tried to save the dying man but in vain. How can you say that our soldiers died in vain?!","id":"3fc7cdc5","ref":"767c2d5b"},{"a1":"be rolling in money","a2":"mieć mnóstwo pieniędzy, spać na pieniądzach","a3":"They dream of the day when they\u0027ll be rolling in money.","id":"b9087055","ref":"767c2d5b"},{"a1":"in writing","a2":"na piśmie","a3":"Please confirm the offer in writing next week.","id":"e46210e7","ref":"767c2d5b"},{"a1":"the lesser of two evils","a2":"mniejsze zło","a3":"Sometimes we have to choose between the lesser of two evils.","id":"e78f2149","ref":"767c2d5b"},{"a1":"come true","a2":"spełniać się","a3":"I wish my dreams would come true one day.","id":"9405c4a2","ref":"767c2d5b"},{"a1":"not have a clue","a2":"nie mieć pojęcia","a3":"I haven\u0027t a clue where she left her book.","id":"b7c8763f","ref":"767c2d5b"},{"a1":"change hands","a2":"przechodzić z rąk do rąk","a3":"The heavyweight title is about to change hands once again.","id":"9e75fb1c","ref":"767c2d5b"},{"a1":"put pressure","a2":"wywierać presję","a3":"The press are putting pressure on the minister to resign.","id":"a0d97765","ref":"767c2d5b"},{"a1":"for short","a2":"w zdrobnieniu","a3":"Her name\u0027s Diana or Di for short.","id":"87a6562c","ref":"767c2d5b"},{"a1":"come in handy","a2":"przydawać się","a3":"Never throw away your notes - they may come in handy one day.","id":"a7189539","ref":"767c2d5b"},{"a1":"in black and white","a2":"na piśmie","a3":"This agreement is invalid, unless you bring it in black and white.","id":"0961ad90","ref":"767c2d5b"},{"a1":"red tape","a2":"biurokracja","a3":"Because of all the red tape she didn\u0027t get her visa on time and had to cancel her holidays in Mexico.","id":"645d7168","ref":"767c2d5b"},{"a1":"commit a blunder","a2":"strzelić gafę","a3":"He committed a blunder asking Sue about her husband, while everybody knows that she is divorced.","id":"3dd1f68a","ref":"767c2d5b"},{"a1":"plead guilty","a2":"przyznać się do winy","a3":"Having seen his face on security video-tape he couldn\u0027t use his alibi any longer and finally pleaded guilty.","id":"eddef02e","ref":"767c2d5b"},{"a1":"red-letter day","a2":"szczególny dzień","a3":"Tomorrow is my red-letter day - I am getting promoted.","id":"0ca819d4","ref":"767c2d5b"},{"a1":"see pink elephants","a2":"widzieć białe myszki","a3":"Tim has a drinking problem. He drinks till he sees pink elephants.","id":"4ecb9adf","ref":"767c2d5b"},{"a1":"a blue movie/film","a2":"film pornograficzny","a3":"Blue movies are rated X, which means that only people of 18 and over can watch them.","id":"e7b9cb2c","ref":"767c2d5b"},{"a1":"beat somebody black and blue","a2":"zbić kogoś na kwaśne jabłko","a3":"Tommy always threatens his little sister that he will beat her black and blue if she tells their parents about his marks at school.","id":"181c07d9","ref":"767c2d5b"},{"a1":"nagging headache","a2":"uporczywy ból głowy","a3":"Jonathan is overworked. That\u0027s why he suffers from these nagging headaches so often.","id":"6fc7bb0f","ref":"767c2d5b"},{"a1":"nagging husband/wife","a2":"zrzędliwy mąż/żona","a3":"I have no idea how she can stand living with such a nagging husband as hers.","id":"aece2d74","ref":"767c2d5b"},{"a1":"chew something over","a2":"przemyśleć coś","a3":"I can\u0027t give you the answer today. I simply need to chew it over.","id":"df41ad71","ref":"767c2d5b"},{"a1":"dead-end relationship","a2":"beznadziejny związek","a3":"Mary is not happy with her marriage - actually, it is a dead-end relationship.","id":"c3428ab2","ref":"767c2d5b"},{"a1":"choose a soft option","a2":"pójść na łatwiznę","a3":"He gets on my nerves! Whenever there is something challenging, he always chooses a soft option.","id":"79d81409","ref":"767c2d5b"},{"a1":"go to somebody\u0027s head","a2":"uderzyć do głowy","a3":"Power and success went to his head - he no longer comes to our parties.","id":"45a19175","ref":"767c2d5b"},{"a1":"keep sth/sb at bay","a2":"trzymać na dystans, nie dopuszczać do siebie","a3":"He always tries to keep his troubles at bay when he is on holiday.","id":"710fea1d","ref":"767c2d5b"},{"a1":"be left stranded","a2":"być zostawionym samemu sobie (z kłopotami), utknąć","a3":"That party was a disaster! Everybody was having fun and I was left stranded with that boring guy who sat next to me.","id":"4e3bf4c8","ref":"767c2d5b"},{"a1":"on one\u0027s own account","a2":"na własne ryzyko","a3":"Well, you can try to run your own business, but remember that it will be on your own account.","id":"ed51ab2b","ref":"767c2d5b"},{"a1":"be at one\u0027s best","a2":"być w najlepszej formie","a3":"There is no doubt he is to win this race - he is at his best now!","id":"9ab6d95a","ref":"767c2d5b"},{"a1":"be in the air","a2":"nierealne, niepewne","a3":"The initial plans to publish this book in May are quite in the air.","id":"98991f9e","ref":"767c2d5b"},{"a1":"a bone of contention","a2":"przedmiot sporu, kość niezgody","a3":"The choice of place for holiday turned out to be a real bone of contention in their family this year.","id":"1b086152","ref":"767c2d5b"},{"a1":"ring the bell","a2":"brzmieć znajomo, kojarzyć się z czymś","a3":"I don\u0027t know where I might have met him, but the name rings the bell.","id":"847a87c2","ref":"767c2d5b"},{"a1":"just in case","a2":"na wszelki wypadek","a3":"We still have plenty of time but let\u0027s take a taxi just in case.","id":"30c191f4","ref":"767c2d5b"},{"a1":"have a narrow escape","a2":"cudem uniknąć czegoś, o mały włos","a3":"He had a narrow escape when he slipped on the stairs.","id":"57307bb8","ref":"767c2d5b"},{"a1":"out of date","a2":"przestarzały, staroświecki","a3":"I don\u0027t like this design - it is absolutely out of date to me.","id":"4eb05441","ref":"767c2d5b"},{"a1":"blind date","a2":"randka w ciemno","a3":"Sheila is so desperate in her search for a husband - she\u0027s decided to have a blind date!","id":"a76b10bc","ref":"767c2d5b"},{"a1":"a day off (to have/take/get)","a2":"mieć wolne","a3":"I think I am overworked - I certainly need a day off!","id":"e0c9da1f","ref":"767c2d5b"},{"a1":"noughts and crosses","a2":"kółko i krzyżyk","a3":"Noughts and Crosses is a very popular game among students sitting on lectures.","id":"bc116dfe","ref":"767c2d5b"},{"a1":"call it a day","a2":"zakończyć coś, przerwać, fajrant","a3":"Why don\u0027t we call it a day and go home?","id":"97557603","ref":"767c2d5b"},{"a1":"safe and sound","a2":"cały i zdrowy","a3":"To everybody\u0027s relief, he returned safe and sound from the storm.","id":"e6f7df3b","ref":"767c2d5b"},{"a1":"at large","a2":"na wolności, na swobodzie","a3":"There are fewer and fewer exotic species living at large.","id":"6055bcff","ref":"767c2d5b"},{"a1":"have a finger in every pie","a2":"wtrącać się we wszystko","a3":"I can\u0027t stand her any longer! She has to have a finger in every pie! Can\u0027t she just mind her own business?","id":"795a1ac7","ref":"767c2d5b"},{"a1":"at first sight","a2":"na pierwszy rzut oka","a3":"At first sight he seems to be a very competent person.","id":"a59118ce","ref":"767c2d5b"},{"a1":"put one\u0027s foot down","a2":"sprzeciwić się","a3":"My boss wanted me to work on weekends but I was brave enough to put my foot down.","id":"9f93d462","ref":"767c2d5b"},{"a1":"be in force","a2":"obowiązywać","a3":"Don\u0027t worry about that - that rule is no longer in force in our office.","id":"c3038ffb","ref":"767c2d5b"},{"a1":"make a fuss about sth","a2":"robić zamieszanie z jakiegoś powodu","a3":"Gosh! It is just a broken glass. Don\u0027t make a fuss about it.","id":"1bee767e","ref":"767c2d5b"},{"a1":"be a wet blanket","a2":"psuć nastrój","a3":"Please somebody make Jane change the subject! With her stories from her childhood, she can be a real wet blanket.","id":"ee0028f2","ref":"767c2d5b"},{"a1":"learn sth by heart","a2":"nauczyć się na pamięć","a3":"There is no rule why these words collocate, you just need to learn them by heart.","id":"4860afb3","ref":"767c2d5b"},{"a1":"by all means","a2":"wszelkimi sposobami, za wszelka cenę","a3":"By all means this guy should work for us - he is the best specialist I have ever seen!","id":"78ae39d7","ref":"767c2d5b"},{"a1":"once and for all","a2":"raz na zawsze","a3":"I tell you once and for all - I am tired of your complaining about your job! There is nothing else you can do.","id":"8ef69d99","ref":"767c2d5b"},{"a1":"be out of order","a2":"nie działać","a3":"I am sorry but this telephone is out of order. You have to go round the corner.","id":"95fdf635","ref":"767c2d5b"},{"a1":"for the sake of","a2":"dla czegoś/kogoś","a3":"I know that this treatment is unpleasant but you should try it for the sake of your health.","id":"2cfd9557","ref":"767c2d5b"},{"a1":"take a shortcut","a2":"pojść na skróty","a3":"I wouldn\u0027t rely on him - he always thinks how to take shortcuts in everything he does.","id":"95e9e834","ref":"767c2d5b"},{"a1":"pull somebody\u0027s leg","a2":"nabierać, drażnić się","a3":"Mary had me fooled for a while, but finally I realized she was just pulling my leg.","id":"93f3d742","ref":"767c2d5b"},{"a1":"beat about/around the bush","a2":"owijać w bawełnę, unikać przejścia do sedna sprawy","a3":"Stop beating about the bush and tell me what the problem is!","id":"a8a6bad8","ref":"767c2d5b"},{"a1":"sell like hot cakes","a2":"sprzedawac sie bardzo szybko","a3":"The album of this new Irish rock group sells like hot cakes - people ask for it everyday.","id":"6c24211d","ref":"767c2d5b"},{"a1":"go for a song","a2":"sprzedać bardzo tanio","a3":"This car went for a song - the owner was leaving the country and wanted a quick sale.","id":"75c2fee2","ref":"767c2d5b"},{"a1":"a gap year","a2":"rok przerwy pomiędzy szkołą średnią a studiami podczas którego podróżuje się i zdobywa doświadczenie","a3":"I\u0027m considering taking a gap year, to develop myself and increase my self-confidence","id":"816c30e2","ref":"767c2d5b"},{"a1":"get up on the wrong side of the bed","a2":"wstać lewą nogą","a3":"You\u0027d better avoid Mark today - he got up on the wrong side of the bed this morning.","id":"a80ee066","ref":"767c2d5b"},{"a1":"whistle in the dark","a2":"dodawać sobie odwagi","a3":"Totally alone in this big house we joked about nightmares, whistling in the dark perhaps.","id":"f1e9d99e","ref":"767c2d5b"},{"a1":"a cold fish","a2":"ktoś niewrażliwy","a3":"He\u0027s such a cold fish - you can never see any emotions on his face.","id":"ebda5180","ref":"767c2d5b"},{"a1":"a drop in the ocean","a2":"kropla w morzu","a3":"We\u0027re grateful for your help although it\u0027s just a a drop in the ocean of our needs.","id":"265871e1","ref":"767c2d5b"},{"a1":"pop the question","a2":"oświadczyć się","a3":"After seven years of dating, I finally popped the question to my girlfriend.","id":"fffb98bf","ref":"767c2d5b"},{"a1":"chicken out","a2":"stchórzyć","a3":"I wanted to ask Mary out but I chickened out at the last moment.","id":"249f8a9a","ref":"767c2d5b"},{"a1":"on cloud nine","a2":"bardzo szczęśliwy, w siódmym niebie","a3":"She has been on cloud nine since she was promoted.","id":"5beeb81e","ref":"767c2d5b"},{"a1":"at heart","a2":"w głębi duszy","a3":"She said she trusted him but at heart she knew he was lying.","id":"8e547733","ref":"767c2d5b"},{"a1":"at random","a2":"losowo","a3":"The burglar didn\u0027t have any plan - he just entered the shop and grabbed things at random.","id":"d7e61304","ref":"767c2d5b"},{"a1":"at short notice","a2":"w ostatniej chwili, bezzwłocznie","a3":"I\u0027m so sorry I ask you for help at such short notice but I didn\u0027t realize this project would be so demanding.","id":"24895557","ref":"767c2d5b"},{"a1":"have sth at one\u0027s fingertips","a2":"mieć coś w małym palcu","a3":"You can always go and ask Tom of anything concerned with maths, he just has it at his fingertips.","id":"cb6a98aa","ref":"767c2d5b"},{"a1":"at the eleventh hour","a2":"w ostatniej chwili","a3":"We were so nervous that he would miss the train but he, as usual, arrived to the railway station at the eleventh hour.","id":"26f44574","ref":"767c2d5b"},{"a1":"shoot the breeze","a2":"paplać","a3":"She can sit with her friend for hours doing nothing but shooting the breeze!","id":"28a3cf6b","ref":"767c2d5b"},{"a1":"by all means","a2":"oczywiście","a3":"By all means we will try to answer any questions, so feel free to ask.","id":"336830d1","ref":"767c2d5b"},{"a1":"for the time being","a2":"na razie","a3":"That is all what we can offer for the time being but the service is still developing.","id":"1e405cbb","ref":"767c2d5b"},{"a1":"in a month of Sundays","a2":"na \"święty nigdy\", nigdy w życiu","a3":"He will never bring you these CDs, not even in a month of Sundays - just forget it.","id":"f4dce9e3","ref":"767c2d5b"},{"a1":"in bad taste","a2":"w złym guście","a3":"Their house is decorated in such bad taste - where did they get the idea of buying these mock rococo chairs to the living room?","id":"2cc33e1b","ref":"767c2d5b"},{"a1":"be in two minds about sth","a2":"być w rozterce, wahać się","a3":"Well, I don\u0027t know. I am still in two minds about buying this car. It\u0027s second-hand you know...","id":"f0b51fbd","ref":"767c2d5b"},{"a1":"be on the air","a2":"być na antenie","a3":"Quiet everybody! Three, two, one ... You are on the air!","id":"27795747","ref":"767c2d5b"},{"a1":"go off the air","a2":"zejść z anteny","a3":"This program was very popular so the information that it went off the air caused a wave of protest.","id":"172c89ff","ref":"767c2d5b"},{"a1":"out of stock","a2":"nie być dostępnym w sprzedaży","a3":"I\u0027m so sorry but this camera is out of stock now. Can I propose a different model within the same price?","id":"c31b41dd","ref":"767c2d5b"},{"a1":"throw somebody in at the deep end","a2":"rzucić kogoś na głęboką wodę","a3":"You want to learn Spanish? There\u0027s no better way than to throw yourself in at the deep end - go to Spain.","id":"92e589d4","ref":"767c2d5b"},{"a1":"be worlds apart","a2":"bardzo się różnić","a3":"I really like this book but I guess it is worlds apart from what the real situation is.","id":"1961b2cd","ref":"767c2d5b"},{"a1":"the tip of the iceberg","a2":"wierzchołek góry lodowej","a3":"The problems we\u0027ve already experienced are just the tip of the iceberg, I\u0027m afraid.","id":"042a5aec","ref":"767c2d5b"},{"a1":"come what may","a2":"niech się dzieje co chce","a3":"I don\u0027t care that he is going to be there with his new girlfriend! I will be at the party tonight come what may.","id":"1b935cc7","ref":"767c2d5b"},{"a1":"first and foremost","a2":"nade wszystko","a3":"We need peace and stability first and foremost - these are the most important things.","id":"33e1f20a","ref":"767c2d5b"},{"a1":"come to terms with sth","a2":"pogodzić się z czymś","a3":"She can\u0027t come to terms with the fact that she was fired for being late all the time.","id":"d5070909","ref":"767c2d5b"},{"a1":"for all the tea in China","a2":"za nic na świecie","a3":"Oh, come on! I am not going to ask him such question! Not for all the tea in China!","id":"7fb3a46b","ref":"767c2d5b"},{"a1":"Boxing Day","a2":"w Anglii - drugi dzień Świąt Bożego Narodzenia","a3":"Boxing Day - the day after Christmas, which is a public holiday in the UK, or the first Monday after Christmas if Christmas is on Friday or Saturday. It is called \u0027Boxing Day\u0027 because traditionally it was the day when servants were given a \u0027Christmas box\u0027","id":"422596f2","ref":"767c2d5b"},{"a1":"to paint the town red","a2":"świetnie się bawić (zwykle chodząc od baru do baru)","a3":"Let\u0027s paint the town red, boys! That was a difficult test and we all did well. We need to celebrate it.","id":"7cdd38fa","ref":"767c2d5b"},{"a1":"to put sb\u0027s back up","a2":"denerwować, drażnić","a3":"The way he discussed things with her really put her back up.","id":"c96e88f9","ref":"767c2d5b"},{"a1":"to call a spade a spade","a2":"nazywać rzeczy po imieniu","a3":"Stop moaning that that you don\u0027t like the idea! Just go to your boss and call a spade a spade!","id":"5998b618","ref":"767c2d5b"},{"a1":"to put the brakes on","a2":"przestać coś robić","a3":"I think we will have to put the brakes on spending so much money on leisure activities.","id":"e8cb9fe4","ref":"767c2d5b"},{"a1":"with bated breath","a2":"ze wstrzymanym oddechem","a3":"They waited for the news with bated breath.","id":"ac300f91","ref":"767c2d5b"},{"a1":"square meal","a2":"porządny, solidny posiłek","a3":"No wonder you feel sick! All you\u0027ve been eating recently are those instant soups! Get yourself one square meal a day and you will be fine.","id":"bac77707","ref":"767c2d5b"},{"a1":"give-and-take","a2":"kompromis","a3":"You can\u0027t insist on having that your way. There must be some sort of give-and-take.","id":"5ad0740c","ref":"767c2d5b"},{"a1":"put sb through hell","a2":"zrobić komuś piekło na ziemi, spowodować cierpienie","a3":"Our boss put us through hell before he admitted that actually it wasn\u0027t our fault that we had failed with the deadline.","id":"b1802b90","ref":"767c2d5b"},{"a1":"to give sb five","a2":"przybić piątkę","a3":"That was great! Give me five!","id":"79fee477","ref":"767c2d5b"},{"a1":"to hold water","a2":"być sensownym, dać się udowodnić (pozytywnie)","a3":"This theory was easy to abolish - the arguments simply didn\u0027t hold water.","id":"783e4078","ref":"767c2d5b"},{"a1":"hush money","a2":"łapówka","a3":"Many politicians are believed to accept hush money.","id":"c1c0c2a1","ref":"767c2d5b"},{"a1":"to eat sb\u0027s words","a2":"odszczekać coś, przyznać się do błędu","a3":"The President went too far. I think that public opinion will force him to eat his words.","id":"9f1a08dd","ref":"767c2d5b"},{"a1":"in sb\u0027s birthday suit","a2":"nago","a3":"He was a very controversial figure - he happened to appear on stage in his birthday suit.","id":"7670b02b","ref":"767c2d5b"},{"a1":"to take the floor","a2":"przemawiać, zabrać głos w dyskusji","a3":"We know the opinion of the prosecutor. Let the defence take the floor now.","id":"418eaf0a","ref":"767c2d5b"},{"a1":"spitting image of sb","a2":"uderzająco podobny do kogoś","a3":"Believe it or not but he is the spitting image of Dan Ackroyd.","id":"2019126f","ref":"767c2d5b"},{"a1":"budding scientist","a2":"obiecujący naukowiec","a3":"The Academy authorities think he is a budding scientist so he is pampered with grants and scholarships.","id":"9bee0923","ref":"767c2d5b"},{"a1":"at the crack of dawn","a2":"o brzasku, o świcie","a3":"We have to set off at the crack of dawn tomorrow - it gets scorching hot during the day and travelling then is not possible.","id":"df4dda10","ref":"767c2d5b"},{"a1":"to know sth like the back of sb\u0027s hand","a2":"znać jak własną kieszeń","a3":"I can be your guide in this city - I grew up here so I know the place like the back of my hand.","id":"8c39eed9","ref":"767c2d5b"},{"a1":"to be as sober as a judge","a2":"zupełnie trzeźwy, trzeźwy jak świnia","a3":"You may not believe me but I know what I saw - I was sober as a judge when it happened.","id":"e4b3dc03","ref":"767c2d5b"},{"a1":"to stick sb\u0027s neck out","a2":"narażać się, podejmować ryzyko","a3":"Jack says he is not a coward, he just doesn\u0027t like to stick his neck out if it isn\u0027t absolutely necessary.","id":"207f5410","ref":"767c2d5b"},{"a1":"hide-and-seek","a2":"zabawa w chowanego","a3":"Let\u0027s play hide-and-seek! I\u0027m seeking first...","id":"b9d5fe0c","ref":"767c2d5b"},{"a1":"to fly off the handle","a2":"wyjść z siebie, wściec się","a3":"I swear - one more remark like this and I will fly off the handle!","id":"fcc55a47","ref":"767c2d5b"},{"a1":"to labour the point","a2":"rozwodzić się nad czymś, wałkować coś","a3":"Don\u0027t even bother asking him! He will labour the point for ages, and I think you need the answer pretty fast.","id":"f1f2e42b","ref":"767c2d5b"},{"a1":"a big noise","a2":"wielka szycha","a3":"This guy is said to be a big noise in drug trafficking. The police have been after him for a long time.","id":"bd6088f1","ref":"767c2d5b"},{"a1":"to be after sb\u0027s own heart","a2":"o podobnych poglądach, upodobaniach","a3":"This guy is after my own heart - I think it is worth making friends with him.","id":"2ee42bfb","ref":"767c2d5b"},{"a1":"to burn rubber","a2":"wciskać gaz do dechy, palić gumy","a3":"He has got another ticket! He simply can\u0027t drive if he doesn\u0027t burn rubber!","id":"4aed02b6","ref":"767c2d5b"},{"a1":"(not) give a toss","a2":"nie obchodzić, nie interesować (w przeczeniach)","a3":"I don\u0027t give a toss that you are tired. You are supposed to finish it today! (nic mnie nie obchodzi, że...)","id":"92c0f035","ref":"767c2d5b"},{"a1":"take a hike!","a2":"spływaj!","a3":"He got so annoying that finally I told him to take a hike.","id":"b90f8a24","ref":"767c2d5b"},{"a1":"Stand and deliver!","a2":"pieniądze albo życie!","a3":"\u0027I said - stand and deliver or the devil he may take ya!\u0027 (Metallica \"Whiskey in the Jar\")","id":"0e4c1007","ref":"767c2d5b"},{"a1":"to be at one\u0027s wits\u0027 end","a2":"odchodzić od zmysłów","a3":"She was at her wits\u0027 end when she learnt that the avalanche was in the area where her kids usually went skiing.","id":"9b028fd6","ref":"767c2d5b"},{"a1":"easy come easy go","a2":"łatwo przyszło, łatwo poszło","a3":"I\u0027ve lost the money you gave me last week - well, easy come easy go.","id":"6c39ca00","ref":"767c2d5b"},{"a1":"to keep sb\u0027s fingers crossed","a2":"trzymać kciuki","a3":"Good luck! I will keep my fingers crossed.","id":"835a87d7","ref":"767c2d5b"},{"a1":"without a shadow of a doubt","a2":"bez cienia wątpliwości","a3":"I can guarantee that - without a shadow of a doubt this car is the best in its class on the market.","id":"4fe4584a","ref":"767c2d5b"},{"a1":"it\u0027s a foregone conclusion","a2":"to jest z góry przesądzone","a3":"Who was to win this match was a foregone conclusion. The team is the national representation after all...","id":"bec32c8c","ref":"767c2d5b"},{"a1":"get straight to the point","a2":"przejść do sedna","a3":"Carol! Could you just get straight to the point? You want to borrow some money, right?","id":"eef57b97","ref":"767c2d5b"},{"a1":"to stab sb in the back","a2":"wbić komuś nóż w plecy","a3":"I thought I can trust him! And he went to the head office and told them everything - he stabbed me in the back!","id":"1fcfc09b","ref":"767c2d5b"},{"a1":"dead easy","a2":"dziecinnie proste","a3":"Listen! Reported Speech is dead easy - I can explain it to you if you want...","id":"ee81afdd","ref":"767c2d5b"},{"a1":"a tough nut to crack","a2":"twardy orzech do zgryzienia","a3":"This project turned out to be a tough nut to crack.","id":"c919a8dd","ref":"767c2d5b"},{"a1":"it isn\u0027t up to scratch","a2":"poniżej oczekiwań, niewystarczająco dobry","a3":"He rejected this market analysis. He said it wasn\u0027t up to scratch.","id":"1ef4d400","ref":"767c2d5b"},{"a1":"to be killing sb","a2":"dobijać, dawać się we znaki","a3":"I had my first horse - riding lesson yesterday and today my back is killing me...","id":"65c04094","ref":"767c2d5b"},{"a1":"to be back on sb\u0027s feet","a2":"pozbierać się po chorobie, stanąć na nogi","a3":"He took a doctor\u0027s leave for a week, but he\u0027s back on his feet now.","id":"bf8a9979","ref":"767c2d5b"},{"a1":"in the middle of nowhere","a2":"w szczerym polu","a3":"Tom didn\u0027t take the map with him so after several hours of going in circles we ended up in the middle of nowhere.","id":"020edc66","ref":"767c2d5b"},{"a1":"off the beaten track","a2":"na odludziu, poza \u0027utartym szlakiem\u0027","a3":"His cottage is off the beaten track, so you may need explicit instructions how to get there.","id":"9dcdb19d","ref":"767c2d5b"},{"a1":"to pick sb\u0027s brains","a2":"zasięgnąć rady (kogoś kto się na tym zna), skonsultować coś","a3":"Terry, I need to pick your brains about the computer software - I\u0027ve heard you are an expert.","id":"f79111a6","ref":"767c2d5b"},{"a1":"(to be) a bit rusty","a2":"\u0027przykurzony\u0027 (o umiejętnościach, znajomości np. języka itp.)","a3":"My apologies if my Spanish is a bit rusty, I hope you understand the intention of the message.","id":"54bfc368","ref":"767c2d5b"},{"a1":"to brush up","a2":"\u0027odkurzyć\u0027, podszlifować (umiejętności, jezyk itp.)","a3":"My French has got a bit rusty, I\u0027m afraid. I will need to brush it up before the holidays.","id":"843c43bf","ref":"767c2d5b"},{"a1":"to get the hang of sth","a2":"\u0027zaczaić\u0027 coś, załapać (jak coś działa, lub na czym polega)","a3":"And then, as I finally got the hang of this new system, everything turned out to be so easy.","id":"d2f8852b","ref":"767c2d5b"},{"a1":"to have a clue","a2":"mieć o czymś pojęcie","a3":"This new secretary is cute and really tries to do her best but, honestly speaking, she doesn\u0027t seem to have a clue what it is all about.","id":"7abf72c6","ref":"767c2d5b"},{"a1":"to have sth on the tip of sb\u0027s tongue","a2":"mieć coś na końcu języka","a3":"Gosh! I had the answer on the tip of my tongue but of course it wasn\u0027t enough to pass the exam...","id":"97fa1809","ref":"767c2d5b"},{"a1":"to slip sb\u0027s mind","a2":"zapomnieć czegoś, wylecieć z pamięci","a3":"I felt so terrible when I bought her these roses... It slipped my mind that she is allergic to them!","id":"3840da0a","ref":"767c2d5b"},{"a1":"a slip of the tongue","a2":"przejęzyczenie","a3":"It was just a slip of the tongue but in politics it may cost you your career.","id":"ac584646","ref":"767c2d5b"},{"a1":"to shoot oneself in the foot","a2":"strzał w stopę (samobój)","a3":"He shot himself in the foot when he decided to cut on public spending - he lost the support immediately.","id":"e49babc6","ref":"767c2d5b"},{"a1":"to rock the boat","a2":"szkodzić np. firmie, w której samemu się pracuje","a3":"I don\u0027t know what he is up to but he rocks the boat! Somebody should tell him it will do him no good.","id":"9bc65461","ref":"767c2d5b"},{"a1":"to miss the point","a2":"nie zrozumieć czegoś, spudłować","a3":"Well, I don\u0027t know what to think about him - he seems to be quite clever but his last speech proved that he missed the whole point of this campaign.","id":"55ef9be3","ref":"767c2d5b"},{"a1":"show-off","a2":"popis, mający na celu zdobycie poklasku","a3":"Don\u0027t worry. We still have the chance. His lawyer\u0027s defence speech was nothing more but a rhetorical show-off.","id":"8d6effde","ref":"767c2d5b"},{"a1":"to rip sb off","a2":"\u0027zedrzeć z kogoś\u0027 (cenowo)","a3":"Don\u0027t go to that hairdresser over there. It\u0027s nothing special but they will rip you off!","id":"3de009ab","ref":"767c2d5b"},{"a1":"to be loaded","a2":"być nadzianym","a3":"Look at the car he is driving! This guy has to be pretty loaded...","id":"006f1467","ref":"767c2d5b"},{"a1":"a backseat driver","a2":"pasażer bez przerwy pouczający kierowcę samochodu","a3":"I hated travelling with my parents - my dad took it patiently but, to tell the truth, my mum was a terrible backseat driver.","id":"b181da0c","ref":"767c2d5b"},{"a1":"a slowcoach","a2":"guzdrała","a3":"Jimmy! Hurry up, please! You\u0027re such a slowcoach! Can\u0027t you move faster?","id":"1c9cbcba","ref":"767c2d5b"},{"a1":"to read sth from cover to cover","a2":"przeczytać coś od deski do deski","a3":"This novel was so thrilling that I simply read it from cover to cover during one night!","id":"a94bb07a","ref":"767c2d5b"},{"a1":"It\u0027s a must","a2":"to konieczność (koniecznie trzeba zobaczyć, przeczytać, etc)","a3":"This movie is a must! It\u0027s a breakthrough in Hollywood business.","id":"75976dda","ref":"767c2d5b"},{"a1":"a cutting/biting remark","a2":"cięta, złośliwa uwaga","a3":"Finally, I was fed up with his biting remarks about my size and I left him.","id":"d14ef1d0","ref":"767c2d5b"},{"a1":"the root of the problem","a2":"źródło problemu","a3":"The root of the problem is that they don\u0027t learn enough to pass this exam.","id":"9178a3b9","ref":"767c2d5b"},{"a1":"a man of few words","a2":"ktoś małomówny","a3":"Michael is a man of few words, but when he speaks, people listen.","id":"142c29b5","ref":"767c2d5b"},{"a1":"to keep one\u0027s nose to the grindstone","a2":"pracować bez wytchnienia","a3":"Just try to keep your nose to the grindstone and you\u0027ll certainly pass the final exam.","id":"1b0d4b08","ref":"767c2d5b"},{"a1":"hands are tied","a2":"mieć związane ręce, nie móc nic zrobić","a3":"I would really like to help you but my hands are tied... I have to wait for Mark\u0027s decision.","id":"69007800","ref":"767c2d5b"},{"a1":"a sharp tongue","a2":"cięty język","a3":"I like her, but sometimes her sharp tongue irritates me so much.","id":"d305081e","ref":"767c2d5b"},{"a1":"the first pancake is always spoiled","a2":"pierwsze koty za płoty","a3":"Don\u0027t worry! The first pancake is always spoiled. Just try again.","id":"6aeb561f","ref":"767c2d5b"},{"a1":"let sleeping dogs lie","a2":"nie wywołuj wilka z lasu","a3":"Just don\u0027t tell her that he\u0027s back in town. I suppose it\u0027s better to let sleeping dogs lie.","id":"0725c6af","ref":"767c2d5b"},{"a1":"in good faith","a2":"w dobrej wierze","a3":"The information is provided in good faith, however we accept no responsibility for the accuracy of the information.","id":"6e9332f4","ref":"767c2d5b"},{"a1":"have your cake and eat it","a2":"wilk syty i owca cała; mieć ciastko i zjeść ciastko","a3":"You can\u0027t have your cake and eat it. If you want high quality you have to pay for it.","id":"98fab457","ref":"767c2d5b"},{"a1":"give sb their due","a2":"oddawać komuś sprawiedliwość","a3":"Mike\u0027s not very talkative, but to give him his due, you can always count on him.","id":"09ce9978","ref":"767c2d5b"},{"a1":"poke/stick your nose into sth","a2":"wtykać nos w","a3":"She\u0027s always poking her nose into other people\u0027s business.","id":"42809fd2","ref":"767c2d5b"},{"a1":"in the interim","a2":"tymczasem","a3":"I\u0027ll be back in few minutes. In the interim please read the extract from the novel.","id":"c3e3d433","ref":"767c2d5b"},{"a1":"to whet sb\u0027s appetite","a2":"zaostrzać apetyt","a3":"The trip was marvellous. We had a great time and the whole experience whetted our appetite for more.","id":"b82f9598","ref":"767c2d5b"},{"a1":"(with your) hands down","a2":"z palcem w nosie, z łatwością","a3":"Don\u0027t stay up all night, his tests are so easy you\u0027ll pass them with your hands down.","id":"b45f5827","ref":"767c2d5b"},{"a1":"to keep sb\u0027s ear to the ground","a2":"dowiadywać sie co w trawie piszczy","a3":"I have no idea what they are up to, but I will keep my ear to the ground. Once I learn what they plan, I\u0027ll let you know.","id":"dd5c9fc6","ref":"767c2d5b"},{"a1":"hindsight is always 20-20","a2":"mądry Polak po szkodzie","a3":"Now I know I should have stayed in that job, but hindsight is always 20-20 - I couldn\u0027t have known it when I was leaving.","id":"73d5cf29","ref":"767c2d5b"},{"a1":"steer away from","a2":"trzymać się z daleka","a3":"If I were you I would steer away from this guy. He is a womaniser - don\u0027t waste your time with him.","id":"692539d1","ref":"767c2d5b"},{"a1":"off your own bat","a2":"z własnej inicjatywy","a3":"Don\u0027t say I told you to do it, you did it off your own bat and I had nothing to do with it.","id":"fd20d42d","ref":"767c2d5b"},{"a1":"dull as ditchwater","a2":"nudny jak flaki z olejem","a3":"The guy I\u0027m going to the wedding with is nice enough, but as dull as ditchwater. I had better take my walkman...","id":"13dcefc9","ref":"767c2d5b"},{"a1":"good riddance (to bad rubbish)","a2":"baba z wozu, koniom lżej","a3":"So, I hear Rupert has left you? Well, good riddance: he gave you nothing but trouble anyway.","id":"99fa5ac9","ref":"767c2d5b"},{"a1":"to have mixed feelings","a2":"mieć mieszane uczucia","a3":"I have mixed feelings about Mark. I like him but I think he has some dark secrets.","id":"b5ab7cfb","ref":"767c2d5b"},{"a1":"to pluck up courage","a2":"zbierać się na odwagę","a3":"After few days Mike decided to pluck up courage and ask Helen out.","id":"53f8f1cf","ref":"767c2d5b"},{"a1":"to save something for a rainy day","a2":"odkładać coś na czarną godzinę","a3":"Don\u0027t spend all your money just like that! You\u0027d better save some for a rainy day.","id":"84a15ec1","ref":"767c2d5b"},{"a1":"to have a sweet tooth","a2":"lubić słodycze","a3":"Kelly has a sweet tooth. She can eat candies and chocolates all day long.","id":"6190c2d3","ref":"767c2d5b"},{"a1":"last but not least","a2":"rzecz równie ważna (mimo, że wymieniona na końcu)","a3":"And last but not least, I would like to thank my parents for all the support they give me.","id":"3679afa0","ref":"767c2d5b"},{"a1":"to muddy the waters","a2":"zaciemniać obraz","a3":"For some reason they want to muddy the waters. I think their business is not quite legal...","id":"dd1b93bb","ref":"767c2d5b"},{"a1":"a sitting duck","a2":"łatwy cel","a3":"Old people who walk after dark in the dimly lit streets are sitting ducks.","id":"651f33b7","ref":"767c2d5b"},{"a1":"to work for peanuts","a2":"pracować za marne grosze","a3":"Sarah says she doesn\u0027t mind working for peanuts as long as she can see that her work is appreciated.","id":"7f3cf38d","ref":"767c2d5b"},{"a1":"to hold the guns","a2":"mieć wszystkie atuty w ręku","a3":"Well, it\u0027s hard to come up with any reasonable argument in this discussion if he holds the guns.","id":"e9049475","ref":"767c2d5b"},{"a1":"the cupboard is bare","a2":"kasa jest pusta","a3":"I would love to go with you sailing but this month the cupboard is bare.","id":"7b4b5976","ref":"767c2d5b"},{"a1":"loony bin","a2":"psychiatryk, wariatkowo","a3":"Gee... Sometimes when I listen to her opinions I can\u0027t help thinking that she qualifies for some loony bin...","id":"a3374d2a","ref":"767c2d5b"},{"a1":"to chase the dragon","a2":"palić opium lub heroinę","a3":"When the police entered the abandoned factory hall, they found a dozen of young people chasing the dragon there.","id":"5e2e657e","ref":"767c2d5b"},{"a1":"to hit the jackpot","a2":"wygrać los na loterii, zgarnąć całą pulę","a3":"\u0027How does it come that he can afford such a car if he works at a construction site!? He must have hit the jackpot or something!\u0027","id":"659e96cf","ref":"767c2d5b"},{"a1":"gallows humour","a2":"wisielczy humor","a3":"The \u0027Pythons\u0027 are famous for their gallows humour.","id":"1d975d39","ref":"767c2d5b"},{"a1":"gold rush","a2":"gorączka złota","a3":"The most famous gold rush was The California Gold Rush that began in 1848.","id":"cf92650c","ref":"767c2d5b"},{"a1":"the end justifies the means","a2":"cel uświęca środki","a3":"Many people strongly oppose the machiavellian approach that the end justifies the means.","id":"00389cbc","ref":"767c2d5b"},{"a1":"to be down in the dumps","a2":"mieć depresję, \u0027doła\u0027","a3":"Well, you can try to ask her out but she is down in the dumps and I can\u0027t promise that she will answer the phone first of all...","id":"694578a9","ref":"767c2d5b"},{"a1":"keep a straight face","a2":"zachowywać powagę, nie wybuchać śmiechem","a3":"Toby can\u0027t tell jokes. He never keeps a straight face and starts laughing right before the punch line.","id":"af6465f8","ref":"767c2d5b"},{"a1":"When hell freezes over!","a2":"prędzej kaktus mi tu wyrośnie!","a3":"No way! Next time I\u0027ll talk to her is when hell freezes over!","id":"f020501b","ref":"767c2d5b"},{"a1":"pretty penny","a2":"niezła sumka","a3":"He hit the jackpot and quite unexpectedly got pretty penny on his bank account.","id":"43cb3edb","ref":"767c2d5b"},{"a1":"to play ducks and drakes","a2":"puszczać kaczki na wodzie","a3":"\u0027It\u0027s incredible! I can\u0027t find any single pebble here!\u0027 \u0027Oh, probably some kids were playing ducks and drakes here and they threw them all to water.\u0027","id":"7077e066","ref":"767c2d5b"},{"a1":"to sling mud at sb","a2":"obrzucić kogoś błotem","a3":"This presidential campaign was nothing more than mud slinging.","id":"d713a1b1","ref":"767c2d5b"},{"a1":"time please!","a2":"zamykamy! (in a pub)","a3":"Time please! These were the last drinks. Please come back tomorrow.","id":"5e186421","ref":"767c2d5b"},{"a1":"from the bottom of one\u0027s heart","a2":"z głębi serca","a3":"I would like to thank you from the bottom of my heart for all your help.","id":"ccce4e0d","ref":"767c2d5b"},{"a1":"a flash in the pan","a2":"słomiany zapał; fiasko; klapa","a3":"He wants to learn foreign languages, but it may be only a flash in the pan.","id":"c820a30b","ref":"767c2d5b"},{"a1":"of one\u0027s own accord","a2":"z własnej woli, inicjatywy","a3":"I didn\u0027t ask him to clean up my car - he did it of his own accord.","id":"f63a80ca","ref":"767c2d5b"},{"a1":"to be well off","a2":"być dobrze sytuowanym, bogatym","a3":"I think they must be well off - judging from their house and the car in the backyard...","id":"f0889cef","ref":"767c2d5b"},{"a1":"to stand a chance","a2":"mieć widoki na powodzenie","a3":"I\u0027d apply for this job if I were you, I think you stand a chance.","id":"a78968ac","ref":"767c2d5b"},{"a1":"have an eye for/on the main chance","a2":"myśleć o własnej korzyści; mieć własny interes na uwadze","a3":"Jerry doesn\u0027t bother about other people and only has an eye on the main chance.","id":"8a5b3edc","ref":"767c2d5b"},{"a1":"to mind one\u0027s own business","a2":"pilnować własnego nosa, interesu","a3":"Why don\u0027t you stop criticizing me?! Mind your own business!","id":"d7e1e973","ref":"767c2d5b"},{"a1":"to be in the know","a2":"być wtajemniczonym w coś","a3":"I should ask Roger; he\u0027s the boss and he\u0027s in the know.","id":"05c2d02e","ref":"767c2d5b"},{"a1":"to repay in kind","a2":"odpłacić, odwdzięczyć się","a3":"If you help a neighbour, he may repay in kind.","id":"8a1905f6","ref":"767c2d5b"},{"a1":"in fits and starts","a2":"nierówno, nieregularnie, sporadycznie, zrywami","a3":"He isn\u0027t very persevering; he only works in fits and starts.","id":"30bce0dc","ref":"767c2d5b"},{"a1":"to break the news to sb","a2":"zakomunikować komuś przykrą wiadomość","a3":"I had the unpleasant duty of breaking the news of John\u0027s death to his wife.","id":"9a27e2be","ref":"767c2d5b"},{"a1":"to have one\u0027s heart in one\u0027s mouth","a2":"mieć duszę na ramieniu; drżeć ze strachu","a3":"When I think of my exam tomorrow, I have my heart in my mouth.","id":"fca7be69","ref":"767c2d5b"},{"a1":"to lose heart","a2":"stracić wiarę w coś","a3":"Don\u0027t lose heart because you cannot solve the problem straight away.","id":"ec60add6","ref":"767c2d5b"},{"a1":"to have one\u0027s heart in the right place","a2":"mieć dobre serce","a3":"He has not a very pleasant manner, but his heart is in the right place.","id":"e0109f87","ref":"767c2d5b"},{"a1":"faint heart never won fair lady","a2":"do odważnych świat należy","a3":"It\u0027s high time we made a decision! C\u0027mon, faint heart never won fair lady.","id":"97b0a617","ref":"767c2d5b"},{"a1":"to land/fall on one\u0027s feet","a2":"spaść na cztery łapy","a3":"Jim is a type of a guy that, no matter what, seems to land on his feet.","id":"7dd4bd3b","ref":"767c2d5b"},{"a1":"my lips are sealed","a2":"nie pisnę ani słowa","a3":"I won\u0027t tell anyone you love Henrietta. My lips are sealed.","id":"d80160bc","ref":"767c2d5b"},{"a1":"bite/snap sb\u0027s head off","a2":"odpyskować","a3":"I only asked if I could borrow the book. There\u0027s no need to bite my head off!","id":"28dba9a9","ref":"767c2d5b"},{"a1":"to one\u0027s heart\u0027s content","a2":"ile dusza zapragnie","a3":"There\u0027s a new restaurant on the corner. For just $10 you can eat to your heart\u0027s content.","id":"ca9a5f68","ref":"767c2d5b"},{"a1":"have one foot in the grave","a2":"być jedną nogą w grobie","a3":"You know this old lady that lives on second floor? She has one foot in the grave but still behaves as if she were 20. ;-)","id":"11fc225c","ref":"767c2d5b"},{"a1":"Every cloud has a silver lining.","a2":"nie ma tego złego, co by na dobre nie wyszło","a3":"Oswald was very depressed after being fired but he found another job in just few days. Well, every cloud has a silver lining.","id":"2b34fd5e","ref":"767c2d5b"},{"a1":"the grass is greener on the other side of the fence","a2":"wszędzie dobrze gdzie nas nie ma","a3":"When you look at other homes, the grass is often greener on the other side of the fence.","id":"4f5a07c0","ref":"767c2d5b"},{"a1":"to get cold feet","a2":"stchórzyć, rozmyślić się","a3":"They\u0027ll be married next week; if Chester doesn\u0027t get cold feet.","id":"9afa8b11","ref":"767c2d5b"},{"a1":"a golden handshake","a2":"duża odprawa","a3":"Ms. Robinson retired early because her company offered her a golden handshake.","id":"b878963b","ref":"767c2d5b"},{"a1":"figure of speech","a2":"przenośnia; zwrot, wyrażenie retoryczne","a3":"When I said it was a battle to the death it was just a figure of speech.","id":"c6c715ae","ref":"767c2d5b"},{"a1":"an early bird","a2":"ranny ptaszek","a3":"My father is an early bird, he gets up at 5.30 every day.","id":"41c33cae","ref":"767c2d5b"},{"a1":"the black sheep (of the family)","a2":"czarna owca (w rodzinie)","a3":"Everybody says he\u0027s the black sheep of the family - he left home when he was 17 and became a singer.","id":"be68d9a4","ref":"767c2d5b"},{"a1":"green with envy","a2":"zielony z zazdrości","a3":"When they see my new boyfriend, all the girls will turn green with envy.","id":"770e9541","ref":"767c2d5b"},{"a1":"leap year","a2":"rok przestępny","a3":"Year 2004 is a leap year, with 29 days in February.","id":"061cbcb6","ref":"767c2d5b"},{"a1":"agony column","a2":"\"napisz do Kasi\", kolumna z poradami dla czytelników","a3":"I just love to read the agony column in teenage magazines. Their problems are sometimes so weird.","id":"e8effcdc","ref":"767c2d5b"},{"a1":"white lie","a2":"niewinne kłamstewko","a3":"White lies are sometimes inevitable in order to protect other people\u0027s feelings.","id":"f747498b","ref":"767c2d5b"},{"a1":"Fort Knox","a2":"bank rezerw federalnych, przenośnie: bardzo dobrze strzeżone miejsce","a3":"My house is now like Fort Knox but I had to do it - I was burgled three times last month.","id":"069b0661","ref":"767c2d5b"},{"a1":"to see red","a2":"wściec się","a3":"When Chris told me he\u0027d crashed my car, I just saw red.","id":"0600951e","ref":"767c2d5b"},{"a1":"the Big Apple","a2":"New York City","a3":"I\u0027m planning to visit the Big Apple this year.","id":"73fd23c6","ref":"767c2d5b"},{"a1":"to take the floor","a2":"zabrać głos","a3":"The Prime Minister will take the floor in budget discussion on Wednesday.","id":"0d6b6bf4","ref":"767c2d5b"},{"a1":"to frame / to be framed","a2":"wrabiać kogoś","a3":"\"Who Framed Roger Rabbit\" is my favourite movie from the nineties.","id":"20ab4ee8","ref":"767c2d5b"},{"a1":"excuse my French","a2":"sorry za słówka","a3":"I really wanted to provide the pronunciation to this fucking word \"ophthalmologist\" but it turned out to be impossible, excuse my French.","id":"5a6cc87a","ref":"767c2d5b"},{"a1":"greasy spoon","a2":"speluna z tanim żarciem","a3":"I\u0027m broke, today we have to eat at this greasy spoon at the corner.","id":"aa062ee9","ref":"767c2d5b"},{"a1":"to get on like a house on fire","a2":"świetnie sie dogadywać","a3":"Tom and Jerry get on like a house on fire. They\u0027ve been friends for years.","id":"9e3a77b1","ref":"767c2d5b"},{"a1":"to play truant","a2":"chodzić na wagary","a3":"More and more children are caught playing truant.","id":"4a7bc51a","ref":"767c2d5b"},{"a1":"make oneself at home","a2":"rozgościć się","a3":"Frank! So many years! Come in and make yourself at home. Something to drink?","id":"b1e73fef","ref":"767c2d5b"},{"a1":"to get hot under the collar","a2":"dostać piany, wściec się","a3":"When he saw his girlfriend winking at the guy sitting next to her, he simply got hot under the collar.","id":"dff010a8","ref":"767c2d5b"},{"a1":"to turn a blind eye","a2":"przymknąć na coś oko; udawać, że się nie widzi czegoś","a3":"The farmer knew that the boys from the neighbourhood stole his apples but he simply turned a blind eye to it.","id":"da559501","ref":"767c2d5b"},{"a1":"a babe in the woods","a2":"bezradny jak dziecko","a3":"When it comes to dealing with computers, he\u0027s a babe in the woods. He definitely needs someone to help.","id":"3bd62050","ref":"767c2d5b"},{"a1":"a shot in the dark","a2":"strzał w ciemno, na chybił trafił","a3":"It was just a shot in the dark. I don\u0027t know what the correct answer is.","id":"12c97dde","ref":"767c2d5b"},{"a1":"to add fuel to the fire/flames","a2":"dolewać oliwy do ognia","a3":"Michael is furious at me. Telling him that I took his book will only add fuel to the fire.","id":"4c74300d","ref":"767c2d5b"},{"a1":"couch potato","a2":"ktoś, kto preferuje siedzący tryb życia - cały dzień siedzi na kanapie, je chipsy i ogląda telewizję ;-)","a3":"Our 9-year-old son is a real couch potato who wants to spend all his free time watching television.","id":"7fab308a","ref":"767c2d5b"},{"a1":"over the counter","a2":"bez recepty","a3":"I\u0027m afraid you can\u0027t buy this medicine over the counter, you must have a prescription.","id":"48905385","ref":"767c2d5b"},{"a1":"to kill two birds with one stone","a2":"upiec dwie pieczenie na jednym ogniu","a3":"By enrolling her son in a hobby class Mary has killed two birds with one stone. Not only is he learning something useful but he is also watching less TV.","id":"29b744ca","ref":"767c2d5b"},{"a1":"to kill somebody with kindness","a2":"zagłaskać kota na śmierć","a3":"My husband is killing me with kindness. Sometimes I just need to be left alone and he wants to spend all day with me.","id":"65ce28fd","ref":"767c2d5b"},{"a1":"be on the crest of a wave","a2":"przeżywać dobry, pomyślny okres; być \"na fali\"","a3":"The Rasmus are currently on the crest of a wave, they are extremely popular among teenagers.","id":"38bf87a0","ref":"767c2d5b"},{"a1":"to run errands","a2":"robić, załatwiać sprawunki","a3":"I have to run errands for my parents after my school.","id":"2d21130b","ref":"767c2d5b"},{"a1":"to toe the line","a2":"podporządkować się","a3":"Two members have been expelled from the party as they didn\u0027t toe the party line in voting.","id":"68d0549c","ref":"767c2d5b"},{"a1":"to play something by ear","a2":"robić coś spontanicznie, improwizować","a3":"If our plan fails, we can always play it by ear. It might work.","id":"91289eea","ref":"767c2d5b"},{"a1":"to be into something","a2":"być czymś zainteresowany, lubić coś","a3":"Don\u0027t ask me about Manga - I am not into it at all.","id":"2cb3d2ee","ref":"767c2d5b"},{"a1":"to go over with a fine-tooth comb","a2":"przeczesać coś","a3":"She went over her boyfriend\u0027s stuff with a fine-tooth comb just to make sure he does not date anybody else.","id":"38e7086c","ref":"767c2d5b"},{"a1":"make oneself scarce","a2":"zmyć sie po cichu","a3":"The atmosphere in the room was getting more and more tense, so I made myself scarce on the first possible occasion.","id":"ed738f51","ref":"767c2d5b"},{"a1":"be in the pay of sb","a2":"być na usługach kogoś (tajnych)","a3":"Hmmm... I have the impression that some data have been leaking from the company since Hans was employed here... Do you think he may be in the pay of our competitor?","id":"296ad8a3","ref":"767c2d5b"},{"a1":"a slap in the face","a2":"policzek","a3":"It was a real slap in the face when she didn\u0027t answer my phone calls.","id":"cf167bdd","ref":"767c2d5b"},{"a1":"to call sb names","a2":"wyzywać kogoś","a3":"He called her names when she refused to date him, which only proved that it was actually a right decision...","id":"594f2644","ref":"767c2d5b"},{"a1":"that\u0027s my funeral","a2":"to mój problem, nic ci do tego","a3":"\u0027You eat too much! You will put on weight!\u0027 \u0027That\u0027s my funeral...\u0027","id":"e783ae1a","ref":"767c2d5b"},{"a1":"on horseback","a2":"wierzchem","a3":"Travelling on horseback took days and one could never be sure that they would reach their destination.","id":"35bfbc88","ref":"767c2d5b"},{"a1":"to be not much of a ...","a2":"nie za dobry ...","a3":"Ugh! She is not much of a singer, I\u0027m afraid.","id":"3b3ab295","ref":"767c2d5b"},{"a1":"leg it","a2":"biegiem!","a3":"What are you waiting for?! Leg it to the nearest newsagent\u0027s and buy this issue - there is an article about your uncle Tim!","id":"a0d1b58d","ref":"767c2d5b"},{"a1":"the grapevine","a2":"poczta pantoflowa","a3":"I heard on/through the grapevine that you are moving to Warsaw, is that true?","id":"dd616b95","ref":"767c2d5b"},{"a1":"to serve him/her right","a2":"dobrze (jemu/jej) tak!","a3":"Frank\u0027s girlfriend has left him?! Serves him right! He behaved like a shmuck!","id":"0c5cd742","ref":"767c2d5b"},{"a1":"to go up in smoke","a2":"spełznąć na niczym","a3":"We wanted to visit my friends that weekend but it turned out that Terry had to work on Saturday and our plans simply went up in smoke.","id":"11a60c78","ref":"767c2d5b"},{"a1":"Get stuffed!","a2":"wypchaj się!","a3":"I tried to be nice to him but finally he went too far! I simply told him to get stuffed...","id":"de8d4a8b","ref":"767c2d5b"},{"a1":"to bury the hatchet","a2":"zakopać topór wojenny","a3":"Of course this old quarrel is long forgotten! Why don\u0027t Kate and Mike bury the hatchet at last?","id":"4776e4d3","ref":"767c2d5b"},{"a1":"to pick up the pieces","a2":"naprawić coś, uporządkować","a3":"After the fire in the factory, it took weeks to pick up the pieces and get production back to normal again.","id":"39538364","ref":"767c2d5b"},{"a1":"to throw the book at someone","a2":"udzielić komuś reprymendy","a3":"My boss threw the book at me for not correcting the report properly.","id":"002c85f8","ref":"767c2d5b"},{"a1":"a vicious circle","a2":"błędne koło","a3":"He thinks he is a failure so he drinks. The more he drinks the more he fails. It\u0027s a vicious circle.","id":"b5d49e77","ref":"767c2d5b"},{"a1":"to take one\u0027s time","a2":"nie śpieszyć się, robić coś powoli","a3":"We don\u0027t need these articles to be translated tomorrow, so relax, take your time and submit them next week.","id":"eb0b0279","ref":"767c2d5b"},{"a1":"to have the last word","a2":"mieć ostatnie słowo","a3":"My father always likes to have the last word in any discussion.","id":"9064b00a","ref":"767c2d5b"},{"a1":"to take something into account","a2":"wziąć coś pod uwagę","a3":"Remember to take his age into account when deciding what kind of work to give him.","id":"4a254819","ref":"767c2d5b"},{"a1":"a blue-eyed boy","a2":"ulubieniec","a3":"Tom was always jealous of his younger brother because he knew Jack was their mother\u0027s blue-eyed boy.","id":"410a6817","ref":"767c2d5b"},{"a1":"to be in the pink","a2":"być zdrowym","a3":"My sister is finally back in the pink after having a bad cold for two weeks.","id":"2c50937e","ref":"767c2d5b"},{"a1":"for a change","a2":"dla odmiany","a3":"She always seemed rather serious so it was nice to see her laugh for a change.","id":"3d1de2ee","ref":"767c2d5b"},{"a1":"not my scene","a2":"nie moja \"działka\"","a3":"I don\u0027t like heavy metal music. It\u0027s not my scene.","id":"c4b6e65e","ref":"767c2d5b"},{"a1":"to fall for someone","a2":"zakochać się","a3":"Julie goes to this pub every night because she has fallen for its barman.","id":"78743d45","ref":"767c2d5b"},{"a1":"to kill time","a2":"zabić czas","a3":"I only read magazines in doctors\u0027 waiting rooms to kill time.","id":"386be3b6","ref":"767c2d5b"},{"a1":"to have a heart of gold","a2":"mieć złote serce","a3":"Mr Brown has a heart of gold, he would do anything to make his children happy.","id":"1ef67ada","ref":"767c2d5b"},{"a1":"Hands off!","a2":"Łapy precz!","a3":"Hands off those chocolates! They are mine!","id":"55546e5f","ref":"767c2d5b"},{"a1":"in a word","a2":"jednym słowem","a3":"She wasn\u0027t able to explain this situation to me. In a word, she is guilty.","id":"745255b6","ref":"767c2d5b"},{"a1":"a stone\u0027s throw","a2":"rzut beretem","a3":"Oh, come on! Go and get me some drinks, the shop is just a stone\u0027s throw from here.","id":"77652eee","ref":"767c2d5b"},{"a1":"Time\u0027s up!","a2":"czas się skończył!","a3":"Time\u0027s up now, put down your pens and leave the class, please.","id":"9d7457c1","ref":"767c2d5b"},{"a1":"for good","a2":"na dobre","a3":"Jane has gone to France - for good. She\u0027s not coming back.","id":"d29d8699","ref":"767c2d5b"},{"a1":"for a laugh","a2":"dla zabawy","a3":"They put salt in his tea just for a laugh but he didn\u0027t find it funny.","id":"9203738a","ref":"767c2d5b"},{"a1":"from scratch","a2":"od samego początku","a3":"I learned Spanish from scratch at university.","id":"021cf698","ref":"767c2d5b"},{"a1":"to cry one\u0027s eyes out","a2":"płakać bardzo mocno, ryczeć","a3":"Julie cried her eyes out when she failed an important exam.","id":"af9bf2e8","ref":"767c2d5b"},{"a1":"from head to foot","a2":"od stóp do glów","a3":"The dog was covered in mud from head to foot.","id":"753b8191","ref":"767c2d5b"},{"a1":"on the road","a2":"w podróży","a3":"Steve\u0027s job involves being on the road six days a week.","id":"059e0ee0","ref":"767c2d5b"},{"a1":"all\u0027s well that ends well","a2":"wszystko dobre, co się dobrze kończy","a3":"The weather was terrible when we arrived in France but after two days it changed completely and we had a wonderful holiday. All\u0027s well that ends well.","id":"ae31872e","ref":"767c2d5b"},{"a1":"against all odds","a2":"pomimo wszystkich przeciwności","a3":"Against all odds, he won that contest and became a well-known actor.","id":"679b67b1","ref":"767c2d5b"},{"a1":"out of the question","a2":"wykluczone","a3":"I will not let my son go to France on his own. It is out of the question.","id":"f58e69c1","ref":"767c2d5b"},{"a1":"to give someone a hand","a2":"pomóc komuś","a3":"Could you please give me a hand with the luggage? It\u0027s really heavy.","id":"0c6dda88","ref":"767c2d5b"},{"a1":"in a nutshell","a2":"krótko mówiąc, w skrócie","a3":"I don\u0027t really like him, in a nutshell, I think he is an idiot.","id":"a4fc96d3","ref":"767c2d5b"},{"a1":"out of the blue","a2":"znienacka, nieoczekiwanie","a3":"The letter came out of the blue - I didn\u0027t expect to hear from him ever again.","id":"56b4f68f","ref":"767c2d5b"},{"a1":"to have a sharp tongue","a2":"mieć cięty język","a3":"I try to avoid discussions with her - she\u0027s got a sharp tongue and she can upset me.","id":"d6b38fe4","ref":"767c2d5b"},{"a1":"to play with fire","a2":"igrać z ogniem","a3":"Tom is negotiating with two publishers at the same time for the same novel. He\u0027s playing with fire.","id":"22d3d4a1","ref":"767c2d5b"},{"a1":"to be in somebody\u0027s shoes","a2":"być na czyimś miejscu","a3":"I wouldn\u0027t like to be in Susan\u0027s shoes - imagine taking that difficult exam again!","id":"9f7e78ad","ref":"767c2d5b"},{"a1":"out of this world","a2":"świetny, doskonały","a3":"This restaurant is rather expensive but the food is really out of this world!","id":"c8c79090","ref":"767c2d5b"},{"a1":"dead on time","a2":"punktualnie","a3":"I can\u0027t be late - Jack always arrives dead on time!","id":"d721c0d2","ref":"767c2d5b"},{"a1":"step by step","a2":"krok po kroku","a3":"Don\u0027t try to teach her everything at one time, do it step by step.","id":"3831390e","ref":"767c2d5b"},{"a1":"to put a stop to something","a2":"kłaść czemuś kres","a3":"He doesn\u0027t work and only spends my sister\u0027s money; I have to put a stop to it!","id":"3c2c2f77","ref":"767c2d5b"},{"a1":"from cover to cover","a2":"od deski do deski","a3":"I always read detective stories from cover to cover; they\u0027re so exciting!","id":"6dba9be8","ref":"767c2d5b"},{"a1":"to give someone a buzz","a2":"zadzwonić do kogoś","a3":"Sorry. I have to go now, but I will give you a buzz later, ok?","id":"640c0892","ref":"767c2d5b"},{"a1":"a piece of cake","a2":"nic trudnego, pestka","a3":"Climbing that mountain was a piece of cake. No problem at all.","id":"19d001df","ref":"767c2d5b"},{"a1":"to spill the beans","a2":"wygadać się, wyjawić sekret","a3":"I showed Tom my present for our mother and asked him not to spill the beans.","id":"bcf58fea","ref":"767c2d5b"},{"a1":"to eat like a horse","a2":"jeść jak koń","a3":"I\u0027m not surprised he\u0027s fat, he eats like a horse!","id":"32b1f53f","ref":"767c2d5b"},{"a1":"to sleep like a log","a2":"spać jak zabity","a3":"Did you sleep well last night? Yes, thanks. Like a log!","id":"b69afb5e","ref":"767c2d5b"},{"a1":"crocodile tears","a2":"krokodyle (nieszczere) łzy","a3":"I don\u0027t feel sorry for her. They\u0027re only crocodile tears.","id":"69e5e8c1","ref":"767c2d5b"},{"a1":"a counsel of despair","a2":"akt rozpaczy","a3":"Her desicion to leave the country after she was fired was a counsel of despair.","id":"c4849fa5","ref":"767c2d5b"},{"a1":"on top of the world","a2":"bardzo szczęsliwy/a","a3":"She\u0027s feeling on top of the world when he won the prize.","id":"24a42cee","ref":"767c2d5b"},{"a1":"to cross one\u0027s mind","a2":"przychodzić do głowy / na myśl","a3":"It never crossed my mind that he could be in love with me.","id":"8dd0f26e","ref":"767c2d5b"},{"a1":"to throw a party","a2":"urządzić przyjęcie, imprezę","a3":"We\u0027re throwing a party for Jim\u0027s birthday next week.","id":"632f55de","ref":"767c2d5b"},{"a1":"the game worth the candle","a2":"gra warta świeczki","a3":"- I\u0027m going to do everything to marry him! - But Ann, is the game worth the candle?!","id":"81abb9bc","ref":"767c2d5b"},{"a1":"to be out of one\u0027s mind","a2":"być szalonym, postradać zmysły","a3":"She must be out of her mind to want to marry such a fool!","id":"5346c596","ref":"767c2d5b"},{"a1":"at times","a2":"czasami, niekiedy","a3":"I think everyone gets a bit lonely at times.","id":"891a7d67","ref":"767c2d5b"},{"a1":"to be in the same boat","a2":"być w tej samej (zwykle złej) sytuacji","a3":"Jane and I are in the same boat; neither of us has got a job.","id":"9011bd52","ref":"767c2d5b"},{"a1":"to take something to heart","a2":"brać sobie coś do serca","a3":"I didn\u0027t really mean that your husband is silly, so don\u0027t take it to heart.","id":"a88ac956","ref":"767c2d5b"},{"a1":"to get the sack","a2":"być wyrzuconym/wylanym z pracy","a3":"Tom wasn\u0027t good enough at work and he got the sack.","id":"1b287f73","ref":"767c2d5b"},{"a1":"to read someone\u0027s mind/thoughts","a2":"czytać komuś w myślach","a3":"We understand each other very well and I sometimes think she reads my mind.","id":"a1367d02","ref":"767c2d5b"},{"a1":"to take someone for a ride","a2":"oszukać kogoś, nabrać","a3":"Be careful when doing business with him; he may take you for a ride.","id":"3c32c308","ref":"767c2d5b"},{"a1":"to take sb/sth seriously","a2":"traktować kogoś/coś poważnie","a3":"Don\u0027t take everything he says seriously; he jokes a lot.","id":"736e8297","ref":"767c2d5b"},{"a1":"Get a move on!","a2":"pośpiesz się!","a3":"Come on, get a move on! I don\u0027t want to be late.","id":"7cb34fb0","ref":"767c2d5b"},{"a1":"to go to pieces","a2":"załamywać się, tracić panowanie nad sobą","a3":"After his child was badly injured in a car accident, he simply went to pieces.","id":"420a5950","ref":"767c2d5b"},{"a1":"to hit the roof","a2":"wściec się","a3":"My parents hit the roof when I told them that I failed my exam again.","id":"5793762e","ref":"767c2d5b"},{"a1":"to have words with somebody","a2":"sprzeczać się, kłócić się","a3":"I think Mark had words with his girlfriend today because he is very nervous.","id":"41750733","ref":"767c2d5b"},{"a1":"in cold blood","a2":"z zimną krwią","a3":"He killed the girl in cold blood just to get the money.","id":"dd50bcf9","ref":"767c2d5b"},{"a1":"time is money","a2":"czas to pieniądz","a3":"Come on, hurry up! Remember, time is money.","id":"097e963d","ref":"767c2d5b"},{"a1":"to pull yourself together","a2":"opanować się, wziąć się w garść","a3":"Pull yourself together and come back to work, please.","id":"73b74be9","ref":"767c2d5b"},{"a1":"in theory","a2":"teoretycznie, w teorii","a3":"His plans always sound great in theory but they don\u0027t work in practice.","id":"6809de8c","ref":"767c2d5b"},{"a1":"take it easy","a2":"nie przejmuj się, wyluzuj się","a3":"Don\u0027t despair if you fail that exam; take it easy.","id":"6b88c639","ref":"767c2d5b"},{"a1":"so what?","a2":"i co z tego?","a3":"She\u0027s angry at you. So what? I don\u0027t like her anyway.","id":"f09e1feb","ref":"767c2d5b"},{"a1":"in the wash","a2":"w praniu","a3":"Oh, I can\u0027t put on my red skirt! It\u0027s in the wash.","id":"b6d225b2","ref":"767c2d5b"},{"a1":"to be in the right","a2":"mieć rację, słuszność","a3":"There\u0027s no need to apologize; you were in the right.","id":"848130c9","ref":"767c2d5b"},{"a1":"to get somebody wrong","a2":"źle, opacznie kogoś zrozumieć","a3":"Don\u0027t get me wrong. I didn\u0027t want to say he was a fool.","id":"f0faf171","ref":"767c2d5b"},{"a1":"out of the ordinary","a2":"niezwykły, specjalny, niecodzienny","a3":"My friend\u0027s paintings are out of the ordinary; I\u0027ve never seen something like that before.","id":"de7e6eae","ref":"767c2d5b"},{"a1":"donkey\u0027s years","a2":"całe wieki","a3":"Mary\u0027s been working in my company for donkey\u0027s years and I won\u0027t sack her now.","id":"1bb3a96a","ref":"767c2d5b"},{"a1":"to take the mickey (out of somebody)","a2":"robić sobie żarty/jaja z kogoś","a3":"Mike was taking the mickey out of me when I was dancing.","id":"37c936de","ref":"767c2d5b"},{"a1":"to keep one\u0027s word","a2":"dotrzymywać słowa","a3":"Sue said she would help me to find a job and I hope she will keep her word.","id":"a4f339c8","ref":"767c2d5b"},{"a1":"dog tired","a2":"bardzo zmęczony","a3":"He\u0027s been working all day and night; he must be dog tired.","id":"e62e2016","ref":"767c2d5b"},{"a1":"to make ends meet","a2":"wiązać koniec z końcem","a3":"They\u0027re really poor; it\u0027s hard for them to make ends meet.","id":"aa234e2f","ref":"767c2d5b"},{"a1":"an arm and a leg","a2":"mnóstwo pieniędzy","a3":"That car is great but it cost me an arm and a leg.","id":"1256e556","ref":"767c2d5b"},{"a1":"a black look","a2":"gniewne, pełne nienawiści spojrzenie","a3":"Mary gave me a black look when I entered the office.","id":"23cb3572","ref":"767c2d5b"},{"a1":"in public","a2":"publicznie","a3":"She feels bad about her divorce and she has never spoken about it in public.","id":"55bcf671","ref":"767c2d5b"},{"a1":"Watch your step!","a2":"Uważaj jak idziesz!","a3":"Watch your step! The floor is very slippery.","id":"2ba026a3","ref":"767c2d5b"},{"a1":"go back on one\u0027s word","a2":"cofnąć dane słowo, wycofać sie z obietnicy","a3":"I promised to give Frank some money and I can\u0027t go back on my word now.","id":"bd04081b","ref":"767c2d5b"},{"a1":"on the dole","a2":"na zasiłku dla bezrobotnych","a3":"She\u0027s been on the dole for two years and she still hasn\u0027t got a job.","id":"bf5100d0","ref":"767c2d5b"},{"a1":"to have a stab at sth","a2":"próbować czegoś","a3":"I\u0027ve never tried diving in my life but I\u0027ll have a stab at it in Egypt.","id":"d9a87274","ref":"767c2d5b"},{"a1":"Get lost!","a2":"Spływaj, zjeżdżaj!","a3":"I can\u0027t stand your behaviour any more. Get lost!","id":"5d862629","ref":"767c2d5b"},{"a1":"pins and needles","a2":"mrowienie, \u0027mrówki\u0027","a3":"I\u0027ve got pins and needles in my leg! I have to move it.","id":"9cf611a6","ref":"767c2d5b"},{"a1":"to be in high spirits","a2":"być w radosnym nastroju","a3":"Mary passed her last exam yesterday and she was in high spirits all day.","id":"131b4ba1","ref":"767c2d5b"},{"a1":"to take sth into your head","a2":"zdecydować się nagle coś zrobić","a3":"He seems to have taken it into his head to ask Ann to marry him.","id":"74b1f8bc","ref":"767c2d5b"},{"a1":"to get sth straight","a2":"wyjaśniać coś","a3":"Let\u0027s get this straight. You\u0027re sure you didn\u0027t leave your wallet at home, right?","id":"e1f5bf71","ref":"767c2d5b"},{"a1":"(all) hot and bothered","a2":"zmieszany, zakłopotany lub zły","a3":"Jim gets all hot and bothered when I mention his ex-girlfriend.","id":"c87309e8","ref":"767c2d5b"},{"a1":"to have butterflies in one\u0027s stomach","a2":"denerwować się, mieć tremę","a3":"I had butterflies in my stomach when I was waiting for the results of my exam yesterday.","id":"7c4930dc","ref":"767c2d5b"},{"a1":"to have a (good) nose for sth","a2":"mieć nosa do czegoś","a3":"He\u0027s a brilliant reporter who has a good nose for interesting stories.","id":"e182da70","ref":"767c2d5b"},{"a1":"as stubborn as a mule","a2":"uparty jak osioł","a3":"I was trying to make my father go to a doctor at last but he\u0027s as stubborn as a mule.","id":"3607742a","ref":"767c2d5b"},{"a1":"over my dead body!","a2":"po moim trupie!","a3":"I want to sell our house. Over my dead body! That house will never be sold.","id":"66a8394a","ref":"767c2d5b"},{"a1":"once in a blue moon","a2":"bardzo rzadko","a3":"I only go to the theatre once in a blue moon; I prefer cinema.","id":"88eb1235","ref":"767c2d5b"},{"a1":"to go to the dogs","a2":"pogarszać się","a3":"The country is going to the dogs; we really need a new government.","id":"f5220d56","ref":"767c2d5b"},{"a1":"to cost a bomb","a2":"kosztować fortunę, masę pieniędzy","a3":"It\u0027s a very beautiful house but I\u0027m afraid it must cost a bomb!","id":"81f31f06","ref":"767c2d5b"},{"a1":"off colour","a2":"marnie, słabo (czuć się, wyglądać)","a3":"Sue was looking off colour when I met her. I\u0027m worried about her.","id":"b75e258b","ref":"767c2d5b"},{"a1":"to have a frog in your throat","a2":"nie móc nic powiedzieć (z powodu suchości w gardle lub ze zdenerwowania)","a3":"The lecturer asked me to present my paper in front of all students but I couldn\u0027t because I had a frog in my throat.","id":"2ed9c55c","ref":"767c2d5b"},{"a1":"a big-head","a2":"zarozumialec, ważniak","a3":"Tom told me that all his friends are less intelligent than he is. He\u0027s such a big head!","id":"2aa62600","ref":"767c2d5b"},{"a1":"to talk rubbish","a2":"mówić bzdury, głupstwa","a3":"I don\u0027t really like Mark; he talks rubbish most of the time.","id":"e2b3dfa3","ref":"767c2d5b"},{"a1":"to talk behind one\u0027s back","a2":"mówić o kimś za jego/jej plecami","a3":"I don\u0027t feel good at work as I know my colleagues are always talking behind my back.","id":"2f0f243e","ref":"767c2d5b"},{"a1":"off the point","a2":"nie na temat","a3":"We were all talking about our jobs so Nick\u0027s comment on his marriage was rather off the point.","id":"a763e7b0","ref":"767c2d5b"},{"a1":"to drop a brick","a2":"powiedzieć coś nietaktownego, nie na miejscu","a3":"I dropped a brick when I told my brother I didn\u0027t like Mary at all; I didn\u0027t know he was seeing her.","id":"929d1a28","ref":"767c2d5b"},{"a1":"to keep sth quiet","a2":"utrzymać coś w tajemnicy","a3":"I didn\u0027t want to worry my sick mother and I managed to keep my divorce quiet for some time.","id":"f0053124","ref":"767c2d5b"},{"a1":"to make head or tail of sth","a2":"zrozumieć coś","a3":"Can you help me? I can\u0027t make head or tail of these instructions on the radio.","id":"39915500","ref":"767c2d5b"},{"a1":"to be all ears","a2":"zamienić się w słuch","a3":"I\u0027m all ears- tell me how it happened that you\u0027ve come back to Poland.","id":"beba712f","ref":"767c2d5b"},{"a1":"by profession","a2":"z zawodu","a3":"My mother works as an English teacher but she\u0027s an economist by profession.","id":"4d3beefe","ref":"767c2d5b"},{"a1":"let alone","a2":"nie mówiąc już o..","a3":"I hardly ever go to the cinema, let alone the theatre.","id":"bb16cbf3","ref":"767c2d5b"},{"a1":"in a sense","a2":"w pewnym sensie","a3":"In a sense she\u0027s right, but I still don\u0027t understand her point of view.","id":"9d5debec","ref":"767c2d5b"},{"a1":"to have green fingers","a2":"mieć smykałkę do ogrodnictwa","a3":"My husband has got green fingers - look at our flowers in the garden.","id":"b2e32f4e","ref":"767c2d5b"},{"a1":"to smell a rat","a2":"podejrzewać, że coś jest źle, nie tak","a3":"Helen smelled a rat when her son started going out every evening so she followed him once and saw him buying drugs near a night club.","id":"b41fd516","ref":"767c2d5b"},{"a1":"to do time","a2":"siedzieć w więzieniu, odsiadywać karę","a3":"The man who attacked my friend last year is doing time for murder now.","id":"fbf88d9a","ref":"767c2d5b"},{"a1":"to have an early night","a2":"pójść wcześnie spać","a3":"I\u0027m going to have an early night tonight because I\u0027m really tired.","id":"fbbc6325","ref":"767c2d5b"},{"a1":"to hammer sth into someone","a2":"wbijać komuś coś do głowy","a3":"My brother and I always had it hammered into us that we should respect old people.","id":"2c68a670","ref":"767c2d5b"},{"a1":"young at heart","a2":"młody duchem","a3":"Although my mother is over fifty, she\u0027s very energetic and young at heart.","id":"417507d8","ref":"767c2d5b"},{"a1":"to get sth off your chest","a2":"wyrzucić coś z siebie, zrzucić ciężar z serca","a3":"I kept on thinking about telling Mark that he hurt me and I was glad to get it off my chest at last.","id":"b8c5b642","ref":"767c2d5b"},{"a1":"to lose face","a2":"stracić twarz, honor","a3":"I guess John thinks he would lose face if he admitted he had made a mistake.","id":"2e77783b","ref":"767c2d5b"},{"a1":"with open arms","a2":"z otwartymi ramionami, chętnie","a3":"I accepted Kate\u0027s invitation to her birthday party with open arms.","id":"fd6aa817","ref":"767c2d5b"},{"a1":"to be in a rut","a2":"popaść w rutynę","a3":"I think I have to change my lifestyle; I\u0027m in a rut.","id":"ff0f4a7b","ref":"767c2d5b"},{"a1":"to cut sth/sb short","a2":"przerywać","a3":"I intended to explain the whole situation to him but he cut me short.","id":"4929c2f3","ref":"767c2d5b"},{"a1":"to take issue with sb","a2":"nie zgadzać się z kimś, sprzeczać się","a3":"My sister took issue with me over my opinion of one of the leading politicians in our country.","id":"c95b185d","ref":"767c2d5b"},{"a1":"to prick up your ears","a2":"nadstawiać uszy/u","a3":"I pricked up my ears when I heard my parents speaking about me.","id":"629d8768","ref":"767c2d5b"},{"a1":"too good to be true","a2":"zbyt piękne, by było prawdziwe","a3":"I still can\u0027t believe I got that job. It\u0027s just too good to be true.","id":"a6647a68","ref":"767c2d5b"},{"a1":"to make it a rule to do sth","a2":"robić coś z zasady, regularnie coś robić","a3":"I make it a rule to eat a lot vegetables.","id":"0a6230ab","ref":"767c2d5b"},{"a1":"off the map","a2":"poza mapą, odległy, daleki","a3":"I can\u0027t remember the name of the place where Jenny lives; it\u0027s a tiny village way off the map.","id":"1962870a","ref":"767c2d5b"},{"a1":"to keep oneself to oneself","a2":"żyć cicho, samemu, bez towarzystwa","a3":"Mary hardly ever goes out with us; she keeps herself to herself.","id":"461bcc7f","ref":"767c2d5b"},{"a1":"to put down roots","a2":"osiąść, zakorzenić się, ustatkować","a3":"He finally put down roots after living and working in many different places.","id":"62e45b9d","ref":"767c2d5b"},{"a1":"to be broke","a2":"być spłukanym, bez kasy","a3":"I\u0027m afraid I can\u0027t lend you any money; I\u0027m absolutely broke.","id":"bfaa817a","ref":"767c2d5b"},{"a1":"to take your life in your hands","a2":"ryzykować własne życie","a3":"Every time my son goes parachuting, he takes his life in his hands.","id":"4713d9f3","ref":"767c2d5b"},{"a1":"to make/pull faces","a2":"robić, stroić miny","a3":"I know that my pupils often make faces behind my back.","id":"2c26fbf7","ref":"767c2d5b"},{"a1":"to make a scene","a2":"robić scenę, awanturę","a3":"Please don\u0027t make a scene. I\u0027ll do what you want.","id":"430509b8","ref":"767c2d5b"},{"a1":"under oath","a2":"pod przysięgą","a3":"I was asked to tell my story under oath at the trial.","id":"61737a85","ref":"767c2d5b"},{"a1":"a bundle of nerves","a2":"kłębek nerwów, bardzo nerwowa osoba","a3":"After all the problems I\u0027ve had recently I\u0027m just a bundle of nerves now.","id":"f5e4a5ab","ref":"767c2d5b"},{"a1":"to swear like a sailor","a2":"klnąć jak szewc","a3":"I don\u0027t like George; he\u0027s vulgar and swears like a sailor.","id":"7ee0b06b","ref":"767c2d5b"},{"a1":"train of thought","a2":"ciąg myśli","a3":"Stop interrupting me or I\u0027ll lose my train of thought.","id":"84f22d3e","ref":"767c2d5b"},{"a1":"scared to death","a2":"śmiertelnie przerażony","a3":"Last night I was scared to death when I discovered that someone was following me.","id":"35d70f5c","ref":"767c2d5b"},{"a1":"to go","a2":"na wynos","a3":"Can I have two small pizzas- to go, please?","id":"4850ff31","ref":"767c2d5b"},{"a1":"as sick as a dog","a2":"bardzo chory","a3":"I was as sick as a dog after eating a hamburger from a fast food restaurant yesterday.","id":"c958ed60","ref":"767c2d5b"},{"a1":"to bite the dust","a2":"umrzeć, przekręcić się, \u0027gryźć ziemię\u0027","a3":"John was already 89 when he bit the dust.","id":"4981a240","ref":"767c2d5b"},{"a1":"curiosity killed the cat","a2":"ciekawość to pierwszy stopień do piekła","a3":"Don\u0027t ask her any questions about her marriage. Remember, curiosity killed the cat.","id":"28314ed1","ref":"767c2d5b"},{"a1":"Achilles heel","a2":"pięta Achillesa","a3":"Speaking in public is my Achilles heel; I\u0027m simply too shy.","id":"5d657432","ref":"767c2d5b"},{"a1":"stark naked","a2":"zupełnie goły, całkiem nagi","a3":"The small children playing on the beach were stark naked.","id":"6d05e0e0","ref":"767c2d5b"},{"a1":"at death\u0027s door","a2":"na łożu śmierci","a3":"My poor grandmother is very ill now and I\u0027m afraid she\u0027s at death\u0027s door.","id":"52fe7c03","ref":"767c2d5b"},{"a1":"to feel it in one\u0027s bones","a2":"czuć to w kościach","a3":"It\u0027s going to be a long and cold winter- I can feel it in my bones.","id":"d86cc93c","ref":"767c2d5b"},{"a1":"to read between the lines","a2":"czytać między wierszami","a3":"He said he was very tired, but, reading between the lines, he simply didn\u0027t feel like coming to my party.","id":"b1460052","ref":"767c2d5b"},{"a1":"rise and shine","a2":"wstawaj!","a3":"Come on! Rise and shine. We\u0027ve got to leave now.","id":"f91f1847","ref":"767c2d5b"},{"a1":"get out of my face!","a2":"zejdź mi z oczu!","a3":"I didn\u0027t ask you for your silly comments. Get out of my face!","id":"d88410fa","ref":"767c2d5b"},{"a1":"written all over one\u0027s face","a2":"wypisane na twarzy","a3":"When Nick was told that he hadn\u0027t won the contest, disappointment was written all over his face.","id":"b422ea1f","ref":"767c2d5b"},{"a1":"a far cry from sth","a2":"zupełnie inny, nie mający nic wspólnego","a3":"This house is a far cry from the one we were shown yesterday; it\u0027s much nicer.","id":"d418119c","ref":"767c2d5b"},{"a1":"as poor as a church mouse","a2":"biedny jak mysz kościelna","a3":"We have to help her; she\u0027s as poor as a church mouse.","id":"71c65ede","ref":"767c2d5b"},{"a1":"it\u0027s now or never","a2":"teraz albo nigdy","a3":"If you really want to speak to me, it\u0027s now or never. I\u0027m leaving tomorrow.","id":"b1ae2e67","ref":"767c2d5b"},{"a1":"to not know whether to laugh or cry","a2":"nie wiedzieć czy się śmiać czy płakać","a3":"When the teacher gave me the test and I looked at the questions, I didn\u0027t know whether to laugh or cry.","id":"ef660b58","ref":"767c2d5b"},{"a1":"to kick a/the habit","a2":"skończyć z nawykiem, rzucić coś","a3":"John used to smoke a lot but he kicked the habit 2 years ago.","id":"c2e62ea0","ref":"767c2d5b"},{"a1":"to come down to earth","a2":"zejść na ziemię","a3":"Come down to earth and stop dreaming about Mark; he doesn\u0027t even like you.","id":"693fc0e5","ref":"767c2d5b"},{"a1":"if my memory serves me correctly","a2":"jeśli mnie pamięć nie myli","a3":"That guy\u0027s name is Ben - if my memory serves me correctly.","id":"92b46556","ref":"767c2d5b"},{"a1":"to give sb a big hand","a2":"głośno oklaskiwać","a3":"The audience gave me a big hand when I finished my speech.","id":"2e0c2e78","ref":"767c2d5b"},{"a1":"a pack of lies","a2":"stek kłamstw","a3":"What Jack told me about you is a pack of lies; I don\u0027t believe him.","id":"e72e4641","ref":"767c2d5b"},{"a1":"in a row","a2":"z rzędu","a3":"It was very cold and it snowed for three days in a row.","id":"b2c997d9","ref":"767c2d5b"},{"a1":"to raise one\u0027s hand against sb","a2":"podnieść na kogoś rękę","a3":"If you ever raise your hand against me, I\u0027ll leave you.","id":"da5d2c48","ref":"767c2d5b"},{"a1":"hale and hearty","a2":"zdrowy, krzepki","a3":"John looks hale and hearty these days and he\u0027s very active.","id":"f73627cd","ref":"767c2d5b"},{"a1":"happy hour","a2":"czas, w którym drinki w pubie są sprzedawane taniej","a3":"Let\u0027s go for a drink to that pub round the corner; it\u0027s happy hour now.","id":"fff7c2a9","ref":"767c2d5b"},{"a1":"to play second fiddle","a2":"grać drugorzędną rolę, pozostawać w cieniu","a3":"Ken doesn\u0027t intend to play second fiddle to her; he wants to be the boss.","id":"0226ade9","ref":"767c2d5b"},{"a1":"to take pains to do sth","a2":"dokładać starań, wkładać dużo wysiłku","a3":"My boss takes pains to select the best employees.","id":"ddeeefd1","ref":"767c2d5b"},{"a1":"to have a word with sb","a2":"zamienić z kimś słowo","a3":"Could I have a word with you about our meeting?","id":"4036b629","ref":"767c2d5b"},{"a1":"to save face","a2":"zachować twarz","a3":"The comment that he made was only an attempt to save face in that difficult situation.","id":"1e649fe5","ref":"767c2d5b"},{"a1":"a little something","a2":"drobnostka, niedrogi prezent","a3":"I want to get a little something for Ben and visit him in the hospital.","id":"1c00507b","ref":"767c2d5b"},{"a1":"a dog\u0027s life","a2":"psie życie","a3":"Without family and friends, it\u0027s a dog\u0027s life.","id":"b3ac1d8f","ref":"767c2d5b"},{"a1":"to drop sb a line","a2":"napisać parę słów do kogoś","a3":"Drop me a line when you\u0027ve got time, ok?","id":"97688792","ref":"767c2d5b"},{"a1":"to live to a grand old age","a2":"żyć bardzo długo, dożyc późnej starości","a3":"Our dog was always very active and lived to a grand old age.","id":"e4066921","ref":"767c2d5b"},{"a1":"as hard as nails","a2":"twardy, nie okazujący emocji","a3":"My supervisor is very kind to me but my boss is as hard as nails.","id":"0fe0a157","ref":"767c2d5b"},{"a1":"to thumb a lift","a2":"zatrzymywać samochód (prosząc o podwiezienie)","a3":"I\u0027m afraid we have no choice and if we want to get out of here we have to thumb a lift.","id":"ab82d822","ref":"767c2d5b"},{"a1":"to do a number on sb","a2":"wykręcić komuś numer","a3":"He really did a number on his ex-girlfriend, making her come back to him and then dumping her.","id":"77432df3","ref":"767c2d5b"},{"a1":"wild horses wouldn\u0027t drag me","a2":"nic mnie nie przekona","a3":"Wild horses wouldn\u0027t drag me to Nick\u0027s party; I don\u0027t like him at all.","id":"a5695ab5","ref":"767c2d5b"},{"a1":"to have a face like thunder","a2":"być wściekłym","a3":"When I told Mark that I was going out with Kate he had a face like thunder as he was attracted to her as well.","id":"97f3c60d","ref":"767c2d5b"},{"a1":"to have both feet on the ground","a2":"stąpać twardo po ziemi","a3":"Susan is very practical and she has both feet on the ground.","id":"44f73e4e","ref":"767c2d5b"},{"a1":"to fall into the wrong hands","a2":"wpaść w złe, nieodpowiednie ręce","a3":"I\u0027m looking for someone responsible to take my puppy; I won\u0027t let it fall into the wrong hands.","id":"b0115cb4","ref":"767c2d5b"},{"a1":"to be on everyone\u0027s lips","a2":"być na ustach wszystkich","a3":"Local government elections which are to take place next week are now on everyone\u0027s lips.","id":"9eb1bf9a","ref":"767c2d5b"},{"a1":"to be head over heels in love","a2":"być zakochanym po uszy","a3":"Jim\u0027s head over heels in love with Monica; he talks only about her.","id":"91d7fb50","ref":"767c2d5b"},{"a1":"to show one\u0027s face","a2":"pokazywać się, pojawiać","a3":"After all the trouble you have caused, don\u0027t you dare to show your face here again!","id":"5005bd33","ref":"767c2d5b"},{"a1":"to miss the boat","a2":"przepuścić okazję, przegapić coś","a3":"Bill missed the boat by sending in his application form 2 days after the closing date.","id":"2341e84b","ref":"767c2d5b"},{"a1":"to have the time of one\u0027s life","a2":"świetnie się bawić, przeżywać coś bardzo miłego","a3":"I took my kids to Disneyland last summer and they had the time of their lives.","id":"cdc1347b","ref":"767c2d5b"},{"a1":"as deaf as a post","a2":"głuchy jak pień","a3":"I\u0027m afraid there\u0027s no point in talking to my grandfather; he\u0027s as deaf as a post.","id":"31801aca","ref":"767c2d5b"},{"a1":"to treat someone like dirt","a2":"traktować kogoś jak śmiecia","a3":"I can\u0027t believe that Mark is still with Ann - she treats him like dirt!","id":"1fa79aae","ref":"767c2d5b"},{"a1":"to burn the midnight oil","a2":"pracować lub uczyć się do późna w nocy","a3":"I had an important exam today so I had to burn the midnight oil yesterday.","id":"e6312b77","ref":"767c2d5b"},{"a1":"on all fours","a2":"na czworakach","a3":"My children love to have me on all fours playing with them.","id":"7b4e66af","ref":"767c2d5b"},{"a1":"as fresh as a daisy","a2":"wyglądający i czujący się rześko","a3":"Although I came back late from the party last night I was as fresh as a daisy in the morning.","id":"80ed6f4b","ref":"767c2d5b"},{"a1":"to put one\u0027s best foot forward","a2":"bardzo się postarać, włożyć w coś dużo wysiłku","a3":"If you really want to pass this exam, you\u0027ll have to put your best foot forward.","id":"c3564e26","ref":"767c2d5b"},{"a1":"from A to Z","a2":"od A do Z; w całości, gruntownie","a3":"I respect Mr Wilson as he\u0027s a brilliant teacher who knows his subject from A to Z.","id":"a799fd07","ref":"767c2d5b"},{"a1":"free and easy","a2":"swobodny, wyluzowany, luźny","a3":"I don\u0027t mind going to work as the atmosphere in my office is free and easy.","id":"4a2b70e8","ref":"767c2d5b"},{"a1":"so what?","a2":"i co z tego? kogo to obchodzi?","a3":"I know that Mary is jealous of me. So what?","id":"ffea3b62","ref":"767c2d5b"},{"a1":"under one\u0027s breath","a2":"pod nosem","a3":"Jack was angry when I told him the bad news and he was muttering something under his breath.","id":"23a0bc58","ref":"767c2d5b"},{"a1":"to bring sth to light","a2":"ujawnić jakieś fakty, informację","a3":"My last conversation with Mary brought to light many things about our relationship which I hadn\u0027t realized before.","id":"2f6e02dd","ref":"767c2d5b"},{"a1":"to make a mess of sth","a2":"zepsuć coś, źle coś zrobić","a3":"I know I\u0027ve made a mess of my exam and I\u0027ll have to take it again.","id":"b92dc004","ref":"767c2d5b"},{"a1":"not harm/hurt a fly","a2":"nie skrzywdzić nawet muchy","a3":"My brother can be irritating and bad-tempered sometimes but he wouldn\u0027t hurt a fly.","id":"9ce85c6d","ref":"767c2d5b"},{"a1":"a stag party/night","a2":"wieczór kawalerski","a3":"Forget about your wives! It\u0027s strictly a stag party.","id":"b44f18a8","ref":"767c2d5b"},{"a1":"before someone\u0027s (very) eyes","a2":"na czyichś oczach","a3":"She took my bicycle before my eyes; she didn\u0027t even ask me for it!","id":"e9a09e07","ref":"767c2d5b"},{"a1":"to turn one\u0027s back on someone","a2":"odwrócić się do kogoś plecami","a3":"Mark disappointed me a few times but I can\u0027t turn my back on him now when he needs me.","id":"5a8de5a5","ref":"767c2d5b"}],"id":"767c2d5b"}